{
  "ticker": "BKTI",
  "company_name": "BK Technologies Corporation",
  "sector": "Technology",
  "industry": "Communication Equipment",
  "description": "BK Technologies Corporation, through its subsidiary, BK Technologies, Inc., engages in the design, manufacture, and marketing of wireless communications products in the United States and internationally. It offers two-way land mobile radios (LMR) that are hand-held (portable) or installed in vehicles (mobile). The company offers KNG Series and BKR Series radios that operate in the P25 digital and analog modes, which are used primarily in government, public safety, military, and state and municipal government agencies, as well as various industrial and commercial enterprises; and BK radio produ",
  "employees": "115",
  "exchange": "ASE",
  "website": "https://www.bktechnologies.com",
  "current_price": 80.74,
  "market_cap": 302306528.0,
  "shares_out": 3744198.0,
  "pe_ratio": 23.335258,
  "financial_data": [
    {
      "fiscal_year": "2021",
      "revenue": 0.0,
      "gross_profit": 0.0,
      "operating_income": 0.0,
      "net_income": 0.0,
      "dna": 0.0,
      "operating_cf": 0.0,
      "capex": 0.0,
      "free_cash_flow": 0.0,
      "dividends_paid": -1172000.0,
      "buybacks": 0.0,
      "total_assets": 0.0,
      "total_liabilities": 0.0,
      "total_equity": 0.0,
      "cash": 0.0,
      "total_debt": 0.0,
      "current_assets": 0.0,
      "current_liabilities": 0.0,
      "shares_outstanding": 0.0,
      "net_wc": 0.0,
      "wc_change": -0.0,
      "capex_abs": 0.0,
      "maint_capex": 0.0,
      "owner_earnings": 0.0,
      "gross_margin_pct": null,
      "rev_growth_pct": null
    },
    {
      "fiscal_year": "2022",
      "revenue": 50951000.0,
      "gross_profit": 9844000.0,
      "operating_income": -11081000.0,
      "net_income": -11633000.0,
      "dna": 1423000.0,
      "operating_cf": -9000000.0,
      "capex": -1750000.0,
      "free_cash_flow": -10750000.0,
      "dividends_paid": -2029000.0,
      "buybacks": 0.0,
      "total_assets": 48832000.0,
      "total_liabilities": 28697000.0,
      "total_equity": 20135000.0,
      "cash": 1918000.0,
      "total_debt": 8730000.0,
      "current_assets": 36217000.0,
      "current_liabilities": 22970000.0,
      "shares_outstanding": 3396859.0,
      "net_wc": 13247000.0,
      "wc_change": -13247000.0,
      "capex_abs": 1750000.0,
      "maint_capex": 1225000.0,
      "owner_earnings": -24682000.0,
      "gross_margin_pct": 19.320523640360346,
      "rev_growth_pct": null
    },
    {
      "fiscal_year": "2023",
      "revenue": 74094000.0,
      "gross_profit": 22236000.0,
      "operating_income": -777000.0,
      "net_income": -2230000.0,
      "dna": 1635000.0,
      "operating_cf": 1655000.0,
      "capex": -2117000.0,
      "free_cash_flow": -462000.0,
      "dividends_paid": 0.0,
      "buybacks": 0.0,
      "total_assets": 49408000.0,
      "total_liabilities": 28097000.0,
      "total_equity": 21311000.0,
      "cash": 3456000.0,
      "total_debt": 8332000.0,
      "current_assets": 37202000.0,
      "current_liabilities": 20418000.0,
      "shares_outstanding": 3577002.0,
      "net_wc": 16784000.0,
      "wc_change": -3537000.0,
      "capex_abs": 2117000.0,
      "maint_capex": 1481900.0,
      "owner_earnings": -5613900.0,
      "gross_margin_pct": 30.010527168191757,
      "rev_growth_pct": 45.4220721870032
    },
    {
      "fiscal_year": "2024",
      "revenue": 76592000.0,
      "gross_profit": 29050000.0,
      "operating_income": 7828000.0,
      "net_income": 8359000.0,
      "dna": 1692000.0,
      "operating_cf": 12765000.0,
      "capex": -2556000.0,
      "free_cash_flow": 10209000.0,
      "dividends_paid": 0.0,
      "buybacks": 0.0,
      "total_assets": 51499000.0,
      "total_liabilities": 21668000.0,
      "total_equity": 29831000.0,
      "cash": 7075000.0,
      "total_debt": 1285000.0,
      "current_assets": 36941000.0,
      "current_liabilities": 13974000.0,
      "shares_outstanding": 3571879.0,
      "net_wc": 22967000.0,
      "wc_change": -6183000.0,
      "capex_abs": 2556000.0,
      "maint_capex": 1789200.0,
      "owner_earnings": 2078800.0,
      "gross_margin_pct": 37.92824315855442,
      "rev_growth_pct": 3.37139309525738
    },
    {
      "fiscal_year": "2025",
      "revenue": 86139000.0,
      "gross_profit": 42027000.0,
      "operating_income": 15987000.0,
      "net_income": 13536000.0,
      "dna": 1778000.0,
      "operating_cf": 19441000.0,
      "capex": -3135000.0,
      "free_cash_flow": 16306000.0,
      "dividends_paid": 0.0,
      "buybacks": -1193000.0,
      "total_assets": 63760000.0,
      "total_liabilities": 19062000.0,
      "total_equity": 44698000.0,
      "cash": 22788000.0,
      "total_debt": 1575000.0,
      "current_assets": 48970000.0,
      "current_liabilities": 11637000.0,
      "shares_outstanding": 3733733.0,
      "net_wc": 37333000.0,
      "wc_change": -14366000.0,
      "capex_abs": 3135000.0,
      "maint_capex": 2194500.0,
      "owner_earnings": -1246500.0,
      "gross_margin_pct": 48.78974680458329,
      "rev_growth_pct": 12.464748276582416
    }
  ],
  "latest_oe": -1246500.0,
  "latest_cash": 22788000.0,
  "latest_debt": 1575000.0,
  "ev": 281093528.0,
  "oe_yield": -0.44344670931021934,
  "roe": 30.283234149178934,
  "debt_equity": 0.03523647590496219,
  "latest_gm": 48.78974680458329,
  "current_ratio": 4.208129242932027,
  "latest_net_income": 13536000.0,
  "latest_dna": 1778000.0,
  "latest_wc_change": -14366000.0,
  "latest_maint_capex": 2194500.0,
  "latest_net_wc": 37333000.0,
  "latest_current_assets": 48970000.0,
  "latest_current_liabilities": 11637000.0,
  "mos_flag": "NO — yield does not compensate for business risk",
  "lolla_signals": [
    "Pricing power (GM 48.8%)",
    "High ROE 30.3%",
    "Low leverage (0.04x D/E)"
  ],
  "s1a": "REVIEW (analyst confirmed) — complex sector: Technology",
  "search_queries": {
    "section_1": [
      "BK Technologies Corporation BKTI revenue predictability recurring demand analysis 2025 2026",
      "BK Technologies Corporation BKTI business model complexity investor circle of competence",
      "BK Technologies Corporation BKTI 10 year earnings outlook business stability forecast"
    ],
    "section_2": [
      "BK Technologies Corporation BKTI competitive moat analysis switching costs brand advantage",
      "BK Technologies Corporation BKTI network effects scale advantages cost leadership",
      "BK Technologies Corporation BKTI patents regulatory barriers intellectual property moat",
      "BK Technologies Corporation BKTI competitive threats risks disruption challenges 2025 2026",
      "BK Technologies Corporation BKTI moat widening narrowing competitive position trend"
    ],
    "section_3": [
      "BK Technologies Corporation BKTI CEO management candor shareholder letter transparency",
      "BK Technologies Corporation BKTI executive compensation insider ownership stock options proxy",
      "BK Technologies Corporation BKTI key man risk CEO succession plan leadership"
    ],
    "section_5": [
      "BK Technologies Corporation BKTI stock valuation fair value analyst price target 2025 2026"
    ],
    "section_6": [
      "BK Technologies Corporation BKTI investor sentiment hype contrarian analysis bias"
    ],
    "section_7": [
      "BK Technologies Corporation BKTI market position monopoly commodity pricing power ecosystem",
      "BK Technologies Corporation BKTI growth engines expansion opportunities critical mass"
    ],
    "section_8": [
      "BK Technologies Corporation BKTI investment thesis bull bear case converging forces"
    ],
    "section_9": [
      "BK Technologies Corporation BKTI investment risk permanent capital loss downside analysis",
      "BK Technologies Corporation BKTI opportunity cost alternative investments comparison"
    ]
  },
  "risk_free_rate": 4.35,
  "maint_capex_ratio": 0.7,
  "fetch_date": "2026-06-16"
}