{
  "ticker": "DFIN",
  "company_name": "Donnelley Financial Solutions, Inc.",
  "sector": "Technology",
  "industry": "Software - Application",
  "description": "Donnelley Financial Solutions, Inc. provides compliance and regulatory software and services in the United States, Asia, Europe, Canada, and internationally. It operates through four segments: Capital Markets  Software Solutions (CM-SS); Capital Markets  Compliance and Communications Management (CM-CCM); Investment Companies  Software Solutions (IC-SS); and Investment Companies  Compliance and Communications Management (IC-CCM). The CM-SS segment provides Venue and ActiveDisclosure solutions to public and private companies to manage public and private transactional and compliance processes",
  "employees": "1750",
  "exchange": "NYQ",
  "website": "https://www.dfinsolutions.com",
  "current_price": 39.84,
  "market_cap": 995297856.0,
  "shares_out": 24982375.0,
  "pe_ratio": 29.080292,
  "financial_data": [
    {
      "fiscal_year": "2021",
      "revenue": null,
      "gross_profit": null,
      "operating_income": null,
      "net_income": null,
      "dna": null,
      "operating_cf": 0.0,
      "capex": 0.0,
      "free_cash_flow": 0.0,
      "dividends_paid": 0.0,
      "buybacks": 0.0,
      "total_assets": 0.0,
      "total_liabilities": 0.0,
      "total_equity": 0.0,
      "cash": 0.0,
      "total_debt": 0.0,
      "current_assets": 0.0,
      "current_liabilities": 0.0,
      "shares_outstanding": 0.0,
      "net_wc": 0.0,
      "wc_change": -0.0,
      "capex_abs": 0.0,
      "maint_capex": 0.0,
      "owner_earnings": null,
      "gross_margin_pct": null,
      "rev_growth_pct": null
    },
    {
      "fiscal_year": "2022",
      "revenue": 833600000.0,
      "gross_profit": 463400000.0,
      "operating_income": 152700000.0,
      "net_income": 102500000.0,
      "dna": 62700000.0,
      "operating_cf": 150200000.0,
      "capex": -54200000.0,
      "free_cash_flow": 96000000.0,
      "dividends_paid": 0.0,
      "buybacks": -164700000.0,
      "total_assets": 828300000.0,
      "total_liabilities": 498800000.0,
      "total_equity": 329500000.0,
      "cash": 34200000.0,
      "total_debt": 213900000.0,
      "current_assets": 228400000.0,
      "current_liabilities": 224800000.0,
      "shares_outstanding": 28900000.0,
      "net_wc": 3600000.0,
      "wc_change": -3600000.0,
      "capex_abs": 54200000.0,
      "maint_capex": 37940000.0,
      "owner_earnings": 123660000.0,
      "gross_margin_pct": 55.59021113243762,
      "rev_growth_pct": null
    },
    {
      "fiscal_year": "2023",
      "revenue": 797200000.0,
      "gross_profit": 463900000.0,
      "operating_income": 119800000.0,
      "net_income": 82200000.0,
      "dna": 72100000.0,
      "operating_cf": 124000000.0,
      "capex": -61800000.0,
      "free_cash_flow": 62200000.0,
      "dividends_paid": 0.0,
      "buybacks": -40300000.0,
      "total_assets": 806900000.0,
      "total_liabilities": 404700000.0,
      "total_equity": 402200000.0,
      "cash": 23100000.0,
      "total_debt": 150600000.0,
      "current_assets": 208500000.0,
      "current_liabilities": 201600000.0,
      "shares_outstanding": 29100000.0,
      "net_wc": 6900000.0,
      "wc_change": -3300000.0,
      "capex_abs": 61800000.0,
      "maint_capex": 43260000.0,
      "owner_earnings": 107740000.0,
      "gross_margin_pct": 58.19116909182137,
      "rev_growth_pct": -4.366602687140119
    },
    {
      "fiscal_year": "2024",
      "revenue": 781900000.0,
      "gross_profit": 484000000.0,
      "operating_income": 143200000.0,
      "net_income": 92400000.0,
      "dna": 69500000.0,
      "operating_cf": 171100000.0,
      "capex": -65900000.0,
      "free_cash_flow": 105200000.0,
      "dividends_paid": 0.0,
      "buybacks": -81600000.0,
      "total_assets": 841600000.0,
      "total_liabilities": 405500000.0,
      "total_equity": 436100000.0,
      "cash": 57300000.0,
      "total_debt": 141400000.0,
      "current_assets": 232500000.0,
      "current_liabilities": 224100000.0,
      "shares_outstanding": 28700000.0,
      "net_wc": 8400000.0,
      "wc_change": -1500000.0,
      "capex_abs": 65900000.0,
      "maint_capex": 46130000.0,
      "owner_earnings": 114270000.0,
      "gross_margin_pct": 61.90049878501087,
      "rev_growth_pct": -1.9192172604114432
    },
    {
      "fiscal_year": "2025",
      "revenue": 767000000.0,
      "gross_profit": 486600000.0,
      "operating_income": 151500000.0,
      "net_income": 32400000.0,
      "dna": 66100000.0,
      "operating_cf": 164900000.0,
      "capex": -57100000.0,
      "free_cash_flow": 107800000.0,
      "dividends_paid": 0.0,
      "buybacks": -185000000.0,
      "total_assets": 800400000.0,
      "total_liabilities": 421200000.0,
      "total_equity": 379200000.0,
      "cash": 24500000.0,
      "total_debt": 178500000.0,
      "current_assets": 211400000.0,
      "current_liabilities": 200000000.0,
      "shares_outstanding": 25600000.0,
      "net_wc": 11400000.0,
      "wc_change": -3000000.0,
      "capex_abs": 57100000.0,
      "maint_capex": 39970000.0,
      "owner_earnings": 55530000.0,
      "gross_margin_pct": 63.44198174706649,
      "rev_growth_pct": -1.9056145287121073
    }
  ],
  "latest_oe": 55530000.0,
  "latest_cash": 24500000.0,
  "latest_debt": 178500000.0,
  "ev": 1149297856.0,
  "oe_yield": 4.8316456617491506,
  "roe": 8.544303797468354,
  "debt_equity": 0.47072784810126583,
  "latest_gm": 63.44198174706649,
  "current_ratio": 1.057,
  "latest_net_income": 32400000.0,
  "latest_dna": 66100000.0,
  "latest_wc_change": -3000000.0,
  "latest_maint_capex": 39970000.0,
  "latest_net_wc": 11400000.0,
  "latest_current_assets": 211400000.0,
  "latest_current_liabilities": 200000000.0,
  "mos_flag": "BORDERLINE — yield is close to risk-free rate",
  "lolla_signals": [
    "Pricing power (GM 63.4%)",
    "Low leverage (0.47x D/E)"
  ],
  "s1a": "REVIEW (analyst confirmed) — complex sector: Technology",
  "search_queries": {
    "section_1": [
      "Donnelley Financial Solutions, Inc. DFIN revenue predictability recurring demand analysis 2025 2026",
      "Donnelley Financial Solutions, Inc. DFIN business model complexity investor circle of competence",
      "Donnelley Financial Solutions, Inc. DFIN 10 year earnings outlook business stability forecast"
    ],
    "section_2": [
      "Donnelley Financial Solutions, Inc. DFIN competitive moat analysis switching costs brand advantage",
      "Donnelley Financial Solutions, Inc. DFIN network effects scale advantages cost leadership",
      "Donnelley Financial Solutions, Inc. DFIN patents regulatory barriers intellectual property moat",
      "Donnelley Financial Solutions, Inc. DFIN competitive threats risks disruption challenges 2025 2026",
      "Donnelley Financial Solutions, Inc. DFIN moat widening narrowing competitive position trend"
    ],
    "section_3": [
      "Donnelley Financial Solutions, Inc. DFIN CEO management candor shareholder letter transparency",
      "Donnelley Financial Solutions, Inc. DFIN executive compensation insider ownership stock options proxy",
      "Donnelley Financial Solutions, Inc. DFIN key man risk CEO succession plan leadership"
    ],
    "section_5": [
      "Donnelley Financial Solutions, Inc. DFIN stock valuation fair value analyst price target 2025 2026"
    ],
    "section_6": [
      "Donnelley Financial Solutions, Inc. DFIN investor sentiment hype contrarian analysis bias"
    ],
    "section_7": [
      "Donnelley Financial Solutions, Inc. DFIN market position monopoly commodity pricing power ecosystem",
      "Donnelley Financial Solutions, Inc. DFIN growth engines expansion opportunities critical mass"
    ],
    "section_8": [
      "Donnelley Financial Solutions, Inc. DFIN investment thesis bull bear case converging forces"
    ],
    "section_9": [
      "Donnelley Financial Solutions, Inc. DFIN investment risk permanent capital loss downside analysis",
      "Donnelley Financial Solutions, Inc. DFIN opportunity cost alternative investments comparison"
    ]
  },
  "risk_free_rate": 4.35,
  "maint_capex_ratio": 0.7,
  "fetch_date": "2026-06-16"
}