{
  "ticker": "EVN",
  "company_name": "Eaton Vance Municipal Income Trust",
  "sector": "Financial Services",
  "industry": "Asset Management",
  "description": "Eaton Vance Municipal Income Trust is a close ended fixed income mutual fund launched and managed by Eaton Vance Management. It invests in the fixed income markets. The fund invests primarily in investment grade municipal obligations of various sectors, such as cogeneration, education, electric utilities, general obligations, healthcare, hospital, housing, transportation, and nursing home. Eaton Vance Municipal Income Trust was formed in 1998 and is domiciled in United States.",
  "employees": "N/A",
  "exchange": "NYQ",
  "website": "https://funds.eatonvance.com/Municipal-Income-Trust-EVN.php",
  "current_price": 10.94,
  "market_cap": 436580896.0,
  "shares_out": 39906847.0,
  "pe_ratio": 1094.0,
  "financial_data": [
    {
      "fiscal_year": "2021",
      "revenue": 0.0,
      "gross_profit": 0.0,
      "operating_income": 0.0,
      "net_income": 0.0,
      "dna": 0.0,
      "operating_cf": null,
      "capex": null,
      "free_cash_flow": null,
      "dividends_paid": null,
      "buybacks": null,
      "total_assets": 0.0,
      "total_liabilities": 0.0,
      "total_equity": 0.0,
      "cash": 10049622.0,
      "total_debt": 0.0,
      "current_assets": 0.0,
      "current_liabilities": 0.0,
      "shares_outstanding": 0.0,
      "net_wc": 0.0,
      "wc_change": -0.0,
      "capex_abs": null,
      "maint_capex": null,
      "owner_earnings": null,
      "gross_margin_pct": null,
      "rev_growth_pct": null
    },
    {
      "fiscal_year": "2022",
      "revenue": -93905603.0,
      "gross_profit": 0.0,
      "operating_income": 0.0,
      "net_income": -95941101.0,
      "dna": 0.0,
      "operating_cf": 79497222.0,
      "capex": 0.0,
      "free_cash_flow": 79497222.0,
      "dividends_paid": -22173944.0,
      "buybacks": 0.0,
      "total_assets": 680760823.0,
      "total_liabilities": 234451583.0,
      "total_equity": 446309240.0,
      "cash": 4852900.0,
      "total_debt": 228999128.0,
      "current_assets": 0.0,
      "current_liabilities": 0.0,
      "shares_outstanding": 39667163.0,
      "net_wc": 0.0,
      "wc_change": -0.0,
      "capex_abs": 0.0,
      "maint_capex": 0.0,
      "owner_earnings": -95941101.0,
      "gross_margin_pct": -0.0,
      "rev_growth_pct": null
    },
    {
      "fiscal_year": "2023",
      "revenue": 15052523.0,
      "gross_profit": 0.0,
      "operating_income": 0.0,
      "net_income": 13290380.0,
      "dna": 0.0,
      "operating_cf": 71803922.0,
      "capex": 0.0,
      "free_cash_flow": 71803922.0,
      "dividends_paid": -18822070.0,
      "buybacks": 0.0,
      "total_assets": 617661785.0,
      "total_liabilities": 176884235.0,
      "total_equity": 440777550.0,
      "cash": 134752.0,
      "total_debt": 171289522.0,
      "current_assets": 0.0,
      "current_liabilities": 0.0,
      "shares_outstanding": 39667163.0,
      "net_wc": 0.0,
      "wc_change": -0.0,
      "capex_abs": 0.0,
      "maint_capex": 0.0,
      "owner_earnings": 13290380.0,
      "gross_margin_pct": 0.0,
      "rev_growth_pct": -116.02941945860248
    },
    {
      "fiscal_year": "2024",
      "revenue": 38566990.0,
      "gross_profit": 0.0,
      "operating_income": 0.0,
      "net_income": 36775573.0,
      "dna": 0.0,
      "operating_cf": 22349313.0,
      "capex": 0.0,
      "free_cash_flow": 22349313.0,
      "dividends_paid": -22634083.0,
      "buybacks": 0.0,
      "total_assets": 650676123.0,
      "total_liabilities": 195757083.0,
      "total_equity": 454919040.0,
      "cash": 39982.0,
      "total_debt": 179593115.0,
      "current_assets": 0.0,
      "current_liabilities": 0.0,
      "shares_outstanding": 39667163.0,
      "net_wc": 0.0,
      "wc_change": -0.0,
      "capex_abs": 0.0,
      "maint_capex": 0.0,
      "owner_earnings": 36775573.0,
      "gross_margin_pct": 0.0,
      "rev_growth_pct": 156.21611739108454
    },
    {
      "fiscal_year": "2025",
      "revenue": 2256263.0,
      "gross_profit": 0.0,
      "operating_income": 0.0,
      "net_income": 423472.0,
      "dna": 0.0,
      "operating_cf": -5703711.0,
      "capex": 0.0,
      "free_cash_flow": -5703711.0,
      "dividends_paid": -24200456.0,
      "buybacks": 0.0,
      "total_assets": 640451705.0,
      "total_liabilities": 207344246.0,
      "total_equity": 433107459.0,
      "cash": 0.0,
      "total_debt": 199543135.0,
      "current_assets": 0.0,
      "current_liabilities": 0.0,
      "shares_outstanding": 39867820.0,
      "net_wc": 0.0,
      "wc_change": -0.0,
      "capex_abs": 0.0,
      "maint_capex": 0.0,
      "owner_earnings": 423472.0,
      "gross_margin_pct": 0.0,
      "rev_growth_pct": -94.14975604785336
    }
  ],
  "latest_oe": 423472.0,
  "latest_cash": 0.0,
  "latest_debt": 199543135.0,
  "ev": 636124031.0,
  "oe_yield": 0.06657066536761602,
  "roe": 0.09777527290288483,
  "debt_equity": 0.4607243095298435,
  "latest_gm": 0.0,
  "current_ratio": 0.0,
  "latest_net_income": 423472.0,
  "latest_dna": 0.0,
  "latest_wc_change": -0.0,
  "latest_maint_capex": 0.0,
  "latest_net_wc": 0.0,
  "latest_current_assets": 0.0,
  "latest_current_liabilities": 0.0,
  "mos_flag": "NO — yield does not compensate for business risk",
  "lolla_signals": [
    "Low leverage (0.46x D/E)"
  ],
  "s1a": "YES — business model is understandable (Financial Services)",
  "search_queries": {
    "section_1": [
      "Eaton Vance Municipal Income Trust EVN revenue predictability recurring demand analysis 2025 2026",
      "Eaton Vance Municipal Income Trust EVN business model complexity investor circle of competence",
      "Eaton Vance Municipal Income Trust EVN 10 year earnings outlook business stability forecast"
    ],
    "section_2": [
      "Eaton Vance Municipal Income Trust EVN competitive moat analysis switching costs brand advantage",
      "Eaton Vance Municipal Income Trust EVN network effects scale advantages cost leadership",
      "Eaton Vance Municipal Income Trust EVN patents regulatory barriers intellectual property moat",
      "Eaton Vance Municipal Income Trust EVN competitive threats risks disruption challenges 2025 2026",
      "Eaton Vance Municipal Income Trust EVN moat widening narrowing competitive position trend"
    ],
    "section_3": [
      "Eaton Vance Municipal Income Trust EVN CEO management candor shareholder letter transparency",
      "Eaton Vance Municipal Income Trust EVN executive compensation insider ownership stock options proxy",
      "Eaton Vance Municipal Income Trust EVN key man risk CEO succession plan leadership"
    ],
    "section_5": [
      "Eaton Vance Municipal Income Trust EVN stock valuation fair value analyst price target 2025 2026"
    ],
    "section_6": [
      "Eaton Vance Municipal Income Trust EVN investor sentiment hype contrarian analysis bias"
    ],
    "section_7": [
      "Eaton Vance Municipal Income Trust EVN market position monopoly commodity pricing power ecosystem",
      "Eaton Vance Municipal Income Trust EVN growth engines expansion opportunities critical mass"
    ],
    "section_8": [
      "Eaton Vance Municipal Income Trust EVN investment thesis bull bear case converging forces"
    ],
    "section_9": [
      "Eaton Vance Municipal Income Trust EVN investment risk permanent capital loss downside analysis",
      "Eaton Vance Municipal Income Trust EVN opportunity cost alternative investments comparison"
    ]
  },
  "risk_free_rate": 4.35,
  "maint_capex_ratio": 0.7,
  "fetch_date": "2026-06-16"
}