{
  "ticker": "FNLC",
  "company_name": "The First Bancorp, Inc.",
  "sector": "Financial Services",
  "industry": "Banks - Regional",
  "description": "The First Bancorp, Inc. operates as the bank holding company for First National Bank that provides a range of banking products and services to individual and corporate customers. It accepts various deposit products, including demand, NOW, time, savings, money market, and certificates of deposit accounts. The company also provides commercial loans, such as mortgage loans to finance investments in real property, which includes retail spaces, offices, industrial buildings, hotels, educational facilities, and other specific or mixed use properties; commercial real estate non-owner occupied loans; ",
  "employees": "278",
  "exchange": "NMS",
  "website": "https://www.thefirst.com",
  "current_price": 30.1,
  "market_cap": 339400320.0,
  "shares_out": 11275758.0,
  "pe_ratio": 9.290124,
  "financial_data": [
    {
      "fiscal_year": "2021",
      "revenue": 0.0,
      "gross_profit": 0.0,
      "operating_income": 0.0,
      "net_income": 0.0,
      "dna": 0.0,
      "operating_cf": 0.0,
      "capex": 0.0,
      "free_cash_flow": 0.0,
      "dividends_paid": 0.0,
      "buybacks": 0.0,
      "total_assets": 0.0,
      "total_liabilities": 0.0,
      "total_equity": 0.0,
      "cash": 0.0,
      "total_debt": 0.0,
      "current_assets": 0.0,
      "current_liabilities": 0.0,
      "shares_outstanding": 0.0,
      "net_wc": 0.0,
      "wc_change": -0.0,
      "capex_abs": 0.0,
      "maint_capex": 0.0,
      "owner_earnings": 0.0,
      "gross_margin_pct": null,
      "rev_growth_pct": null
    },
    {
      "fiscal_year": "2022",
      "revenue": 93040000.0,
      "gross_profit": 0.0,
      "operating_income": 0.0,
      "net_income": 38990000.0,
      "dna": 1984000.0,
      "operating_cf": 41213000.0,
      "capex": -1404000.0,
      "free_cash_flow": 39809000.0,
      "dividends_paid": -14779000.0,
      "buybacks": -277000.0,
      "total_assets": 2739178000.0,
      "total_liabilities": 2510255000.0,
      "total_equity": 228923000.0,
      "cash": 26421000.0,
      "total_debt": 39074000.0,
      "current_assets": 0.0,
      "current_liabilities": 0.0,
      "shares_outstanding": 11045186.0,
      "net_wc": 0.0,
      "wc_change": -0.0,
      "capex_abs": 1404000.0,
      "maint_capex": 982799.9999999999,
      "owner_earnings": 39991200.0,
      "gross_margin_pct": 0.0,
      "rev_growth_pct": null
    },
    {
      "fiscal_year": "2023",
      "revenue": 80648000.0,
      "gross_profit": 0.0,
      "operating_income": 0.0,
      "net_income": 29518000.0,
      "dna": 2107000.0,
      "operating_cf": 36919000.0,
      "capex": -2635000.0,
      "free_cash_flow": 34284000.0,
      "dividends_paid": -15418000.0,
      "buybacks": -250000.0,
      "total_assets": 2946698000.0,
      "total_liabilities": 2703619000.0,
      "total_equity": 243079000.0,
      "cash": 35430000.0,
      "total_debt": 20076000.0,
      "current_assets": 0.0,
      "current_liabilities": 0.0,
      "shares_outstanding": 11098057.0,
      "net_wc": 0.0,
      "wc_change": -0.0,
      "capex_abs": 2635000.0,
      "maint_capex": 1844499.9999999998,
      "owner_earnings": 29780500.0,
      "gross_margin_pct": 0.0,
      "rev_growth_pct": -13.319002579535688
    },
    {
      "fiscal_year": "2024",
      "revenue": 80503000.0,
      "gross_profit": 0.0,
      "operating_income": 0.0,
      "net_income": 27045000.0,
      "dna": 2209000.0,
      "operating_cf": 26047000.0,
      "capex": -1475000.0,
      "free_cash_flow": 24572000.0,
      "dividends_paid": -15803000.0,
      "buybacks": -212000.0,
      "total_assets": 3157010000.0,
      "total_liabilities": 2904517000.0,
      "total_equity": 252493000.0,
      "cash": 49736000.0,
      "total_debt": 95000000.0,
      "current_assets": 0.0,
      "current_liabilities": 0.0,
      "shares_outstanding": 11155528.0,
      "net_wc": 0.0,
      "wc_change": -0.0,
      "capex_abs": 1475000.0,
      "maint_capex": 1032499.9999999999,
      "owner_earnings": 28221500.0,
      "gross_margin_pct": 0.0,
      "rev_growth_pct": -0.17979367126277346
    },
    {
      "fiscal_year": "2025",
      "revenue": 94767000.0,
      "gross_profit": 0.0,
      "operating_income": 0.0,
      "net_income": 34394000.0,
      "dna": 2208000.0,
      "operating_cf": 37814000.0,
      "capex": -3220000.0,
      "free_cash_flow": 34594000.0,
      "dividends_paid": -16347000.0,
      "buybacks": -282000.0,
      "total_assets": 3166303000.0,
      "total_liabilities": 2883160000.0,
      "total_equity": 283143000.0,
      "cash": 31903000.0,
      "total_debt": 137500000.0,
      "current_assets": 0.0,
      "current_liabilities": 0.0,
      "shares_outstanding": 11222363.0,
      "net_wc": 0.0,
      "wc_change": -0.0,
      "capex_abs": 3220000.0,
      "maint_capex": 2254000.0,
      "owner_earnings": 34348000.0,
      "gross_margin_pct": 0.0,
      "rev_growth_pct": 17.71859433809919
    }
  ],
  "latest_oe": 34348000.0,
  "latest_cash": 31903000.0,
  "latest_debt": 137500000.0,
  "ev": 444997320.0,
  "oe_yield": 7.718698171036175,
  "roe": 12.14721889645868,
  "debt_equity": 0.48562034025209877,
  "latest_gm": 0.0,
  "current_ratio": 0.0,
  "latest_net_income": 34394000.0,
  "latest_dna": 2208000.0,
  "latest_wc_change": -0.0,
  "latest_maint_capex": 2254000.0,
  "latest_net_wc": 0.0,
  "latest_current_assets": 0.0,
  "latest_current_liabilities": 0.0,
  "mos_flag": "YES — yield is attractive vs. risk-free rate",
  "lolla_signals": [
    "OE growing avg inf% p.a.",
    "Low leverage (0.49x D/E)"
  ],
  "s1a": "YES — business model is understandable (Financial Services)",
  "search_queries": {
    "section_1": [
      "The First Bancorp, Inc. FNLC revenue predictability recurring demand analysis 2025 2026",
      "The First Bancorp, Inc. FNLC business model complexity investor circle of competence",
      "The First Bancorp, Inc. FNLC 10 year earnings outlook business stability forecast"
    ],
    "section_2": [
      "The First Bancorp, Inc. FNLC competitive moat analysis switching costs brand advantage",
      "The First Bancorp, Inc. FNLC network effects scale advantages cost leadership",
      "The First Bancorp, Inc. FNLC patents regulatory barriers intellectual property moat",
      "The First Bancorp, Inc. FNLC competitive threats risks disruption challenges 2025 2026",
      "The First Bancorp, Inc. FNLC moat widening narrowing competitive position trend"
    ],
    "section_3": [
      "The First Bancorp, Inc. FNLC CEO management candor shareholder letter transparency",
      "The First Bancorp, Inc. FNLC executive compensation insider ownership stock options proxy",
      "The First Bancorp, Inc. FNLC key man risk CEO succession plan leadership"
    ],
    "section_5": [
      "The First Bancorp, Inc. FNLC stock valuation fair value analyst price target 2025 2026"
    ],
    "section_6": [
      "The First Bancorp, Inc. FNLC investor sentiment hype contrarian analysis bias"
    ],
    "section_7": [
      "The First Bancorp, Inc. FNLC market position monopoly commodity pricing power ecosystem",
      "The First Bancorp, Inc. FNLC growth engines expansion opportunities critical mass"
    ],
    "section_8": [
      "The First Bancorp, Inc. FNLC investment thesis bull bear case converging forces"
    ],
    "section_9": [
      "The First Bancorp, Inc. FNLC investment risk permanent capital loss downside analysis",
      "The First Bancorp, Inc. FNLC opportunity cost alternative investments comparison"
    ]
  },
  "risk_free_rate": 4.35,
  "maint_capex_ratio": 0.7,
  "fetch_date": "2026-06-16"
}