{
  "ticker": "GPK",
  "company_name": "Graphic Packaging Holding Company",
  "sector": "Consumer Cyclical",
  "industry": "Packaging & Containers",
  "description": "Graphic Packaging Holding Company, together with its subsidiaries, engages in the design, production, and sale of consumer packaging products to brands in food, beverage, foodservice, household, and other consumer products in the Americas, Europe, and the Asia Pacific. It operates through two segments, Americas Paperboard Packaging and International Paperboard Packaging. The Americas Paperboard Packaging segment includes paperboard packaging sold primarily to consumer packaged goods (CPG) companies serving the food, beverage and consumer product markets and cups, lids and food containers sold ",
  "employees": "23000",
  "exchange": "NYQ",
  "website": "https://www.graphicpkg.com",
  "current_price": 10.97,
  "market_cap": 3245884672.0,
  "shares_out": 295887387.0,
  "pe_ratio": 11.923913,
  "financial_data": [
    {
      "fiscal_year": "2021",
      "revenue": 0.0,
      "gross_profit": 0.0,
      "operating_income": 0.0,
      "net_income": 0.0,
      "dna": 0.0,
      "operating_cf": 0.0,
      "capex": 0.0,
      "free_cash_flow": 0.0,
      "dividends_paid": 0.0,
      "buybacks": 0.0,
      "total_assets": 0.0,
      "total_liabilities": 0.0,
      "total_equity": 0.0,
      "cash": 0.0,
      "total_debt": 0.0,
      "current_assets": 0.0,
      "current_liabilities": 0.0,
      "shares_outstanding": 0.0,
      "net_wc": 0.0,
      "wc_change": -0.0,
      "capex_abs": 0.0,
      "maint_capex": 0.0,
      "owner_earnings": 0.0,
      "gross_margin_pct": null,
      "rev_growth_pct": null
    },
    {
      "fiscal_year": "2022",
      "revenue": 9440000000.0,
      "gross_profit": 1830000000.0,
      "operating_income": 1037000000.0,
      "net_income": 522000000.0,
      "dna": 553000000.0,
      "operating_cf": 1090000000.0,
      "capex": -549000000.0,
      "free_cash_flow": 541000000.0,
      "dividends_paid": -92000000.0,
      "buybacks": -46000000.0,
      "total_assets": 10328000000.0,
      "total_liabilities": 8178000000.0,
      "total_equity": 2149000000.0,
      "cash": 150000000.0,
      "total_debt": 5503000000.0,
      "current_assets": 2706000000.0,
      "current_liabilities": 1933000000.0,
      "shares_outstanding": 307116089.0,
      "net_wc": 773000000.0,
      "wc_change": -773000000.0,
      "capex_abs": 549000000.0,
      "maint_capex": 384300000.0,
      "owner_earnings": -82300000.0,
      "gross_margin_pct": 19.385593220338983,
      "rev_growth_pct": null
    },
    {
      "fiscal_year": "2023",
      "revenue": 9428000000.0,
      "gross_profit": 2117000000.0,
      "operating_income": 1248000000.0,
      "net_income": 723000000.0,
      "dna": 619000000.0,
      "operating_cf": 1144000000.0,
      "capex": -804000000.0,
      "free_cash_flow": 340000000.0,
      "dividends_paid": -123000000.0,
      "buybacks": -76000000.0,
      "total_assets": 11175000000.0,
      "total_liabilities": 8393000000.0,
      "total_equity": 2781000000.0,
      "cash": 162000000.0,
      "total_debt": 5435000000.0,
      "current_assets": 2845000000.0,
      "current_liabilities": 2589000000.0,
      "shares_outstanding": 306058815.0,
      "net_wc": 256000000.0,
      "wc_change": 517000000.0,
      "capex_abs": 804000000.0,
      "maint_capex": 562800000.0,
      "owner_earnings": 1296200000.0,
      "gross_margin_pct": 22.45439117522274,
      "rev_growth_pct": -0.12711864406779183
    },
    {
      "fiscal_year": "2024",
      "revenue": 8807000000.0,
      "gross_profit": 1962000000.0,
      "operating_income": 1124000000.0,
      "net_income": 658000000.0,
      "dna": 557000000.0,
      "operating_cf": 840000000.0,
      "capex": -1203000000.0,
      "free_cash_flow": -363000000.0,
      "dividends_paid": -122000000.0,
      "buybacks": -225000000.0,
      "total_assets": 11144000000.0,
      "total_liabilities": 8131000000.0,
      "total_equity": 3012000000.0,
      "cash": 157000000.0,
      "total_debt": 5247000000.0,
      "current_assets": 2784000000.0,
      "current_liabilities": 1903000000.0,
      "shares_outstanding": 300163372.0,
      "net_wc": 881000000.0,
      "wc_change": -625000000.0,
      "capex_abs": 1203000000.0,
      "maint_capex": 842100000.0,
      "owner_earnings": -252100000.0,
      "gross_margin_pct": 22.27773362098331,
      "rev_growth_pct": -6.586762834111159
    },
    {
      "fiscal_year": "2025",
      "revenue": 8617000000.0,
      "gross_profit": 1602000000.0,
      "operating_income": 845000000.0,
      "net_income": 444000000.0,
      "dna": 536000000.0,
      "operating_cf": 841000000.0,
      "capex": -922000000.0,
      "free_cash_flow": -81000000.0,
      "dividends_paid": -128000000.0,
      "buybacks": -184000000.0,
      "total_assets": 11775000000.0,
      "total_liabilities": 8438000000.0,
      "total_equity": 3336000000.0,
      "cash": 261000000.0,
      "total_debt": 5638000000.0,
      "current_assets": 2923000000.0,
      "current_liabilities": 2244000000.0,
      "shares_outstanding": 295128049.0,
      "net_wc": 679000000.0,
      "wc_change": 202000000.0,
      "capex_abs": 922000000.0,
      "maint_capex": 645400000.0,
      "owner_earnings": 536600000.0,
      "gross_margin_pct": 18.591157015202505,
      "rev_growth_pct": -2.157374815487678
    }
  ],
  "latest_oe": 536600000.0,
  "latest_cash": 261000000.0,
  "latest_debt": 5638000000.0,
  "ev": 8622884672.0,
  "oe_yield": 6.222975493832513,
  "roe": 13.309352517985612,
  "debt_equity": 1.6900479616306954,
  "latest_gm": 18.591157015202505,
  "current_ratio": 1.302584670231729,
  "latest_net_income": 444000000.0,
  "latest_dna": 536000000.0,
  "latest_wc_change": 202000000.0,
  "latest_maint_capex": 645400000.0,
  "latest_net_wc": 679000000.0,
  "latest_current_assets": 2923000000.0,
  "latest_current_liabilities": 2244000000.0,
  "mos_flag": "BORDERLINE — yield is close to risk-free rate",
  "lolla_signals": [],
  "s1a": "YES — business model is understandable (Consumer Cyclical)",
  "search_queries": {
    "section_1": [
      "Graphic Packaging Holding Company GPK revenue predictability recurring demand analysis 2025 2026",
      "Graphic Packaging Holding Company GPK business model complexity investor circle of competence",
      "Graphic Packaging Holding Company GPK 10 year earnings outlook business stability forecast"
    ],
    "section_2": [
      "Graphic Packaging Holding Company GPK competitive moat analysis switching costs brand advantage",
      "Graphic Packaging Holding Company GPK network effects scale advantages cost leadership",
      "Graphic Packaging Holding Company GPK patents regulatory barriers intellectual property moat",
      "Graphic Packaging Holding Company GPK competitive threats risks disruption challenges 2025 2026",
      "Graphic Packaging Holding Company GPK moat widening narrowing competitive position trend"
    ],
    "section_3": [
      "Graphic Packaging Holding Company GPK CEO management candor shareholder letter transparency",
      "Graphic Packaging Holding Company GPK executive compensation insider ownership stock options proxy",
      "Graphic Packaging Holding Company GPK key man risk CEO succession plan leadership"
    ],
    "section_5": [
      "Graphic Packaging Holding Company GPK stock valuation fair value analyst price target 2025 2026"
    ],
    "section_6": [
      "Graphic Packaging Holding Company GPK investor sentiment hype contrarian analysis bias"
    ],
    "section_7": [
      "Graphic Packaging Holding Company GPK market position monopoly commodity pricing power ecosystem",
      "Graphic Packaging Holding Company GPK growth engines expansion opportunities critical mass"
    ],
    "section_8": [
      "Graphic Packaging Holding Company GPK investment thesis bull bear case converging forces"
    ],
    "section_9": [
      "Graphic Packaging Holding Company GPK investment risk permanent capital loss downside analysis",
      "Graphic Packaging Holding Company GPK opportunity cost alternative investments comparison"
    ]
  },
  "risk_free_rate": 4.35,
  "maint_capex_ratio": 0.7,
  "fetch_date": "2026-06-16"
}