{
  "ticker": "IBP",
  "company_name": "Installed Building Products, Inc.",
  "sector": "Consumer Cyclical",
  "industry": "Residential Construction",
  "description": "Installed Building Products, Inc., together with its subsidiaries, engages in the installation of insulation for residential and commercial builders in the United States. It operates through three segments: Installation, Distribution, and Manufacturing Operations. It offers a range of insulation materials, such as fiberglass and cellulose, and spray foam insulation materials. It is also involved in the installation of insulation and sealant materials in various areas of a structure, which includes basement and crawl space, building envelope, attic, and acoustical applications. In addition, the",
  "employees": "10400",
  "exchange": "NYQ",
  "website": "https://www.installedbuildingproducts.com",
  "current_price": 208.59,
  "market_cap": 5619562496.0,
  "shares_out": 26940710.0,
  "pe_ratio": 22.261473,
  "financial_data": [
    {
      "fiscal_year": "2021",
      "revenue": 0.0,
      "gross_profit": 0.0,
      "operating_income": 0.0,
      "net_income": 0.0,
      "dna": 0.0,
      "operating_cf": 0.0,
      "capex": 0.0,
      "free_cash_flow": 0.0,
      "dividends_paid": 0.0,
      "buybacks": 0.0,
      "total_assets": 0.0,
      "total_liabilities": 0.0,
      "total_equity": 0.0,
      "cash": 0.0,
      "total_debt": 0.0,
      "current_assets": 0.0,
      "current_liabilities": 0.0,
      "shares_outstanding": 0.0,
      "net_wc": 0.0,
      "wc_change": -0.0,
      "capex_abs": 0.0,
      "maint_capex": 0.0,
      "owner_earnings": 0.0,
      "gross_margin_pct": null,
      "rev_growth_pct": null
    },
    {
      "fiscal_year": "2022",
      "revenue": 2669800000.0,
      "gross_profit": 827800000.0,
      "operating_income": 329300000.0,
      "net_income": 223400000.0,
      "dna": 117700000.0,
      "operating_cf": 277900000.0,
      "capex": -45600000.0,
      "free_cash_flow": 232300000.0,
      "dividends_paid": -62700000.0,
      "buybacks": -137600000.0,
      "total_assets": 1778900000.0,
      "total_liabilities": 1285400000.0,
      "total_equity": 493500000.0,
      "cash": 229600000.0,
      "total_debt": 946000000.0,
      "current_assets": 884400000.0,
      "current_liabilities": 328100000.0,
      "shares_outstanding": 28306482.0,
      "net_wc": 556300000.0,
      "wc_change": -556300000.0,
      "capex_abs": 45600000.0,
      "maint_capex": 31919999.999999996,
      "owner_earnings": -247120000.0,
      "gross_margin_pct": 31.00606787025245,
      "rev_growth_pct": null
    },
    {
      "fiscal_year": "2023",
      "revenue": 2778600000.0,
      "gross_profit": 930700000.0,
      "operating_income": 369100000.0,
      "net_income": 243700000.0,
      "dna": 125700000.0,
      "operating_cf": 340200000.0,
      "capex": -61600000.0,
      "free_cash_flow": 278600000.0,
      "dividends_paid": -63100000.0,
      "buybacks": -6300000.0,
      "total_assets": 1981300000.0,
      "total_liabilities": 1311000000.0,
      "total_equity": 670300000.0,
      "cash": 386500000.0,
      "total_debt": 954800000.0,
      "current_assets": 1070000000.0,
      "current_liabilities": 346400000.0,
      "shares_outstanding": 28367338.0,
      "net_wc": 723600000.0,
      "wc_change": -167300000.0,
      "capex_abs": 61600000.0,
      "maint_capex": 43120000.0,
      "owner_earnings": 158980000.0,
      "gross_margin_pct": 33.49528539552293,
      "rev_growth_pct": 4.075211626339059
    },
    {
      "fiscal_year": "2024",
      "revenue": 2941300000.0,
      "gross_profit": 994500000.0,
      "operating_income": 387400000.0,
      "net_income": 256600000.0,
      "dna": 134500000.0,
      "operating_cf": 340000000.0,
      "capex": -88600000.0,
      "free_cash_flow": 251400000.0,
      "dividends_paid": -84700000.0,
      "buybacks": -145300000.0,
      "total_assets": 2059900000.0,
      "total_liabilities": 1354600000.0,
      "total_equity": 705300000.0,
      "cash": 327600000.0,
      "total_debt": 978300000.0,
      "current_assets": 1054900000.0,
      "current_liabilities": 359000000.0,
      "shares_outstanding": 27758491.0,
      "net_wc": 695900000.0,
      "wc_change": 27700000.0,
      "capex_abs": 88600000.0,
      "maint_capex": 62019999.99999999,
      "owner_earnings": 356780000.0,
      "gross_margin_pct": 33.81157991364363,
      "rev_growth_pct": 5.8554667818325745
    },
    {
      "fiscal_year": "2025",
      "revenue": 2970800000.0,
      "gross_profit": 1009300000.0,
      "operating_income": 386400000.0,
      "net_income": 265400000.0,
      "dna": 144900000.0,
      "operating_cf": 371400000.0,
      "capex": -70600000.0,
      "free_cash_flow": 300800000.0,
      "dividends_paid": -87600000.0,
      "buybacks": -172600000.0,
      "total_assets": 2068000000.0,
      "total_liabilities": 1358100000.0,
      "total_equity": 709900000.0,
      "cash": 321900000.0,
      "total_debt": 991700000.0,
      "current_assets": 1042600000.0,
      "current_liabilities": 344200000.0,
      "shares_outstanding": 26975227.0,
      "net_wc": 698400000.0,
      "wc_change": -2500000.0,
      "capex_abs": 70600000.0,
      "maint_capex": 49420000.0,
      "owner_earnings": 358380000.0,
      "gross_margin_pct": 33.97401373367443,
      "rev_growth_pct": 1.0029578757692281
    }
  ],
  "latest_oe": 358380000.0,
  "latest_cash": 321900000.0,
  "latest_debt": 991700000.0,
  "ev": 6289362496.0,
  "oe_yield": 5.698192785483866,
  "roe": 37.38554726017749,
  "debt_equity": 1.396957317932103,
  "latest_gm": 33.97401373367443,
  "current_ratio": 3.029052876234747,
  "latest_net_income": 265400000.0,
  "latest_dna": 144900000.0,
  "latest_wc_change": -2500000.0,
  "latest_maint_capex": 49420000.0,
  "latest_net_wc": 698400000.0,
  "latest_current_assets": 1042600000.0,
  "latest_current_liabilities": 344200000.0,
  "mos_flag": "BORDERLINE — yield is close to risk-free rate",
  "lolla_signals": [
    "High ROE 37.4%"
  ],
  "s1a": "YES — business model is understandable (Consumer Cyclical)",
  "search_queries": {
    "section_1": [
      "Installed Building Products, Inc. IBP revenue predictability recurring demand analysis 2025 2026",
      "Installed Building Products, Inc. IBP business model complexity investor circle of competence",
      "Installed Building Products, Inc. IBP 10 year earnings outlook business stability forecast"
    ],
    "section_2": [
      "Installed Building Products, Inc. IBP competitive moat analysis switching costs brand advantage",
      "Installed Building Products, Inc. IBP network effects scale advantages cost leadership",
      "Installed Building Products, Inc. IBP patents regulatory barriers intellectual property moat",
      "Installed Building Products, Inc. IBP competitive threats risks disruption challenges 2025 2026",
      "Installed Building Products, Inc. IBP moat widening narrowing competitive position trend"
    ],
    "section_3": [
      "Installed Building Products, Inc. IBP CEO management candor shareholder letter transparency",
      "Installed Building Products, Inc. IBP executive compensation insider ownership stock options proxy",
      "Installed Building Products, Inc. IBP key man risk CEO succession plan leadership"
    ],
    "section_5": [
      "Installed Building Products, Inc. IBP stock valuation fair value analyst price target 2025 2026"
    ],
    "section_6": [
      "Installed Building Products, Inc. IBP investor sentiment hype contrarian analysis bias"
    ],
    "section_7": [
      "Installed Building Products, Inc. IBP market position monopoly commodity pricing power ecosystem",
      "Installed Building Products, Inc. IBP growth engines expansion opportunities critical mass"
    ],
    "section_8": [
      "Installed Building Products, Inc. IBP investment thesis bull bear case converging forces"
    ],
    "section_9": [
      "Installed Building Products, Inc. IBP investment risk permanent capital loss downside analysis",
      "Installed Building Products, Inc. IBP opportunity cost alternative investments comparison"
    ]
  },
  "risk_free_rate": 4.35,
  "maint_capex_ratio": 0.7,
  "fetch_date": "2026-06-16"
}