{
  "ticker": "KMT",
  "company_name": "Kennametal Inc.",
  "sector": "Industrials",
  "industry": "Tools & Accessories",
  "description": "Kennametal Inc. engages in development and application of tungsten carbides, ceramics, and hard materials and solutions worldwide. It operates through two segments, Metal Cutting and Infrastructure. The Metal Cutting segment offers milling, hole making, turning, threading, and toolmaking systems used in the manufacture of airframes, aero engines, trucks and automobiles, ships, and various types of industrial equipment under the Kennametal, WIDIA, WIDIA Hanita, and WIDIA GTD brands through its direct sales force, a network of independent and national distributors, integrated supplier channels, ",
  "employees": "8100",
  "exchange": "NYQ",
  "website": "https://www.kennametal.com",
  "current_price": 35.55,
  "market_cap": 2709269248.0,
  "shares_out": 76210103.0,
  "pe_ratio": 19.97191,
  "financial_data": [
    {
      "fiscal_year": "2021",
      "revenue": 0.0,
      "gross_profit": 0.0,
      "operating_income": 0.0,
      "net_income": 0.0,
      "dna": 0.0,
      "operating_cf": 0.0,
      "capex": 0.0,
      "free_cash_flow": 0.0,
      "dividends_paid": 0.0,
      "buybacks": 0.0,
      "total_assets": null,
      "total_liabilities": null,
      "total_equity": null,
      "cash": null,
      "total_debt": null,
      "current_assets": null,
      "current_liabilities": null,
      "shares_outstanding": null,
      "net_wc": null,
      "wc_change": -0.0,
      "capex_abs": 0.0,
      "maint_capex": 0.0,
      "owner_earnings": 0.0,
      "gross_margin_pct": null,
      "rev_growth_pct": null
    },
    {
      "fiscal_year": "2022",
      "revenue": 2012456000.0,
      "gross_profit": 647977000.0,
      "operating_income": 215896000.0,
      "net_income": 144623000.0,
      "dna": 131678000.0,
      "operating_cf": 181444000.0,
      "capex": -96924000.0,
      "free_cash_flow": 84520000.0,
      "dividends_paid": -66565000.0,
      "buybacks": -85542000.0,
      "total_assets": 2573524000.0,
      "total_liabilities": 1282277000.0,
      "total_equity": 1252577000.0,
      "cash": 85586000.0,
      "total_debt": 663279000.0,
      "current_assets": 1024708000.0,
      "current_liabilities": 485649000.0,
      "shares_outstanding": 81337000.0,
      "net_wc": 539059000.0,
      "wc_change": -0.0,
      "capex_abs": 96924000.0,
      "maint_capex": 67846800.0,
      "owner_earnings": 208454200.0,
      "gross_margin_pct": 32.19831887007716,
      "rev_growth_pct": null
    },
    {
      "fiscal_year": "2023",
      "revenue": 2078184000.0,
      "gross_profit": 646439000.0,
      "operating_income": 196523000.0,
      "net_income": 118459000.0,
      "dna": 134025000.0,
      "operating_cf": 257945000.0,
      "capex": -94385000.0,
      "free_cash_flow": 163560000.0,
      "dividends_paid": -64524000.0,
      "buybacks": -49290000.0,
      "total_assets": 2547234000.0,
      "total_liabilities": 1233066000.0,
      "total_equity": 1275447000.0,
      "cash": 106021000.0,
      "total_debt": 639418000.0,
      "current_assets": 1026789000.0,
      "current_liabilities": 433975000.0,
      "shares_outstanding": 79835000.0,
      "net_wc": 592814000.0,
      "wc_change": -53755000.0,
      "capex_abs": 94385000.0,
      "maint_capex": 66069499.99999999,
      "owner_earnings": 132659500.0,
      "gross_margin_pct": 31.105955969250076,
      "rev_growth_pct": 3.2660589846436494
    },
    {
      "fiscal_year": "2024",
      "revenue": 2046899000.0,
      "gross_profit": 627093000.0,
      "operating_income": 182375000.0,
      "net_income": 109323000.0,
      "dna": 134687000.0,
      "operating_cf": 277108000.0,
      "capex": -107561000.0,
      "free_cash_flow": 169547000.0,
      "dividends_paid": -63431000.0,
      "buybacks": -65574000.0,
      "total_assets": 2503758000.0,
      "total_liabilities": 1215159000.0,
      "total_equity": 1249875000.0,
      "cash": 127971000.0,
      "total_debt": 645754000.0,
      "current_assets": 1002592000.0,
      "current_liabilities": 415961000.0,
      "shares_outstanding": 77889000.0,
      "net_wc": 586631000.0,
      "wc_change": 6183000.0,
      "capex_abs": 107561000.0,
      "maint_capex": 75292700.0,
      "owner_earnings": 174900300.0,
      "gross_margin_pct": 30.636245364329163,
      "rev_growth_pct": -1.5054008692204301
    },
    {
      "fiscal_year": "2025",
      "revenue": 1966845000.0,
      "gross_profit": 598070000.0,
      "operating_income": 156448000.0,
      "net_income": 93125000.0,
      "dna": 136496000.0,
      "operating_cf": 208324000.0,
      "capex": -88971000.0,
      "free_cash_flow": 119353000.0,
      "dividends_paid": -61852000.0,
      "buybacks": -60120000.0,
      "total_assets": 2545412000.0,
      "total_liabilities": 1220764000.0,
      "total_equity": 1283979000.0,
      "cash": 140540000.0,
      "total_debt": 643360000.0,
      "current_assets": 1039270000.0,
      "current_liabilities": 422329000.0,
      "shares_outstanding": 76012000.0,
      "net_wc": 616941000.0,
      "wc_change": -30310000.0,
      "capex_abs": 88971000.0,
      "maint_capex": 62279699.99999999,
      "owner_earnings": 137031300.0,
      "gross_margin_pct": 30.407581685389545,
      "rev_growth_pct": -3.9109892574084038
    }
  ],
  "latest_oe": 137031300.0,
  "latest_cash": 140540000.0,
  "latest_debt": 643360000.0,
  "ev": 3212089248.0,
  "oe_yield": 4.26611122606018,
  "roe": 7.25284447798601,
  "debt_equity": 0.5010673850584784,
  "latest_gm": 30.407581685389545,
  "current_ratio": 2.460806622325249,
  "latest_net_income": 93125000.0,
  "latest_dna": 136496000.0,
  "latest_wc_change": -30310000.0,
  "latest_maint_capex": 62279699.99999999,
  "latest_net_wc": 616941000.0,
  "latest_current_assets": 1039270000.0,
  "latest_current_liabilities": 422329000.0,
  "mos_flag": "NO — yield does not compensate for business risk",
  "lolla_signals": [
    "OE growing avg inf% p.a."
  ],
  "s1a": "YES — business model is understandable (Industrials)",
  "search_queries": {
    "section_1": [
      "Kennametal Inc. KMT revenue predictability recurring demand analysis 2025 2026",
      "Kennametal Inc. KMT business model complexity investor circle of competence",
      "Kennametal Inc. KMT 10 year earnings outlook business stability forecast"
    ],
    "section_2": [
      "Kennametal Inc. KMT competitive moat analysis switching costs brand advantage",
      "Kennametal Inc. KMT network effects scale advantages cost leadership",
      "Kennametal Inc. KMT patents regulatory barriers intellectual property moat",
      "Kennametal Inc. KMT competitive threats risks disruption challenges 2025 2026",
      "Kennametal Inc. KMT moat widening narrowing competitive position trend"
    ],
    "section_3": [
      "Kennametal Inc. KMT CEO management candor shareholder letter transparency",
      "Kennametal Inc. KMT executive compensation insider ownership stock options proxy",
      "Kennametal Inc. KMT key man risk CEO succession plan leadership"
    ],
    "section_5": [
      "Kennametal Inc. KMT stock valuation fair value analyst price target 2025 2026"
    ],
    "section_6": [
      "Kennametal Inc. KMT investor sentiment hype contrarian analysis bias"
    ],
    "section_7": [
      "Kennametal Inc. KMT market position monopoly commodity pricing power ecosystem",
      "Kennametal Inc. KMT growth engines expansion opportunities critical mass"
    ],
    "section_8": [
      "Kennametal Inc. KMT investment thesis bull bear case converging forces"
    ],
    "section_9": [
      "Kennametal Inc. KMT investment risk permanent capital loss downside analysis",
      "Kennametal Inc. KMT opportunity cost alternative investments comparison"
    ]
  },
  "risk_free_rate": 4.35,
  "maint_capex_ratio": 0.7,
  "fetch_date": "2026-06-16"
}