{
  "ticker": "MPAA",
  "company_name": "Motorcar Parts of America, Inc.",
  "sector": "Consumer Cyclical",
  "industry": "Auto Parts",
  "description": "Motorcar Parts of America, Inc. manufactures, remanufactures, and distributes heavy-duty truck, industrial, marine, and agricultural application replacement parts in the United States. It operates through three segments: Hard Parts, Test Solutions and Diagnostic Equipment, and Heavy Duty. The company offers light duty rotating electrical products, including alternators and starters; wheel hub assemblies and bearings; brake-related products comprising brake calipers, brake boosters, brake rotors, brake pads, and brake master cylinders; and turbochargers. It also provides test solutions and diag",
  "employees": "5600",
  "exchange": "NMS",
  "website": "https://www.motorcarparts.com",
  "current_price": 14.85,
  "market_cap": 281033568.0,
  "shares_out": 18924818.0,
  "pe_ratio": 23.951612,
  "financial_data": [
    {
      "fiscal_year": "2022",
      "revenue": null,
      "gross_profit": null,
      "operating_income": null,
      "net_income": null,
      "dna": null,
      "operating_cf": 0.0,
      "capex": 0.0,
      "free_cash_flow": 0.0,
      "dividends_paid": 0.0,
      "buybacks": 0.0,
      "total_assets": 0.0,
      "total_liabilities": 0.0,
      "total_equity": 0.0,
      "cash": 0.0,
      "total_debt": 0.0,
      "current_assets": 0.0,
      "current_liabilities": 0.0,
      "shares_outstanding": 0.0,
      "net_wc": 0.0,
      "wc_change": -0.0,
      "capex_abs": 0.0,
      "maint_capex": 0.0,
      "owner_earnings": null,
      "gross_margin_pct": null,
      "rev_growth_pct": null
    },
    {
      "fiscal_year": "2023",
      "revenue": 683074000.0,
      "gross_profit": 113962000.0,
      "operating_income": 27155000.0,
      "net_income": -4207000.0,
      "dna": 12444000.0,
      "operating_cf": -21754000.0,
      "capex": -4201000.0,
      "free_cash_flow": -25955000.0,
      "dividends_paid": 0.0,
      "buybacks": 0.0,
      "total_assets": 1028565000.0,
      "total_liabilities": 708090000.0,
      "total_equity": 320475000.0,
      "cash": 11596000.0,
      "total_debt": 277222000.0,
      "current_assets": 537478000.0,
      "current_liabilities": 382592000.0,
      "shares_outstanding": 19494615.0,
      "net_wc": 154886000.0,
      "wc_change": -154886000.0,
      "capex_abs": 4201000.0,
      "maint_capex": 2940700.0,
      "owner_earnings": -149589700.0,
      "gross_margin_pct": 16.683697520327225,
      "rev_growth_pct": null
    },
    {
      "fiscal_year": "2024",
      "revenue": 717684000.0,
      "gross_profit": 132551000.0,
      "operating_income": 42306000.0,
      "net_income": -49244000.0,
      "dna": 11619000.0,
      "operating_cf": 39172000.0,
      "capex": -1000000.0,
      "free_cash_flow": 38172000.0,
      "dividends_paid": 0.0,
      "buybacks": 0.0,
      "total_assets": 1012002000.0,
      "total_liabilities": 726892000.0,
      "total_equity": 285110000.0,
      "cash": 13974000.0,
      "total_debt": 239335000.0,
      "current_assets": 560459000.0,
      "current_liabilities": 404425000.0,
      "shares_outstanding": 19662380.0,
      "net_wc": 156034000.0,
      "wc_change": -1148000.0,
      "capex_abs": 1000000.0,
      "maint_capex": 700000.0,
      "owner_earnings": -39473000.0,
      "gross_margin_pct": 18.469270598201994,
      "rev_growth_pct": 5.066800961535645
    },
    {
      "fiscal_year": "2025",
      "revenue": 757354000.0,
      "gross_profit": 153828000.0,
      "operating_income": 55815000.0,
      "net_income": -19470000.0,
      "dna": 10400000.0,
      "operating_cf": 45477000.0,
      "capex": -4578000.0,
      "free_cash_flow": 40899000.0,
      "dividends_paid": 0.0,
      "buybacks": -4832000.0,
      "total_assets": 957636000.0,
      "total_liabilities": 699937000.0,
      "total_equity": 257699000.0,
      "cash": 9429000.0,
      "total_debt": 201284000.0,
      "current_assets": 511471000.0,
      "current_liabilities": 351025000.0,
      "shares_outstanding": 19435706.0,
      "net_wc": 160446000.0,
      "wc_change": -4412000.0,
      "capex_abs": 4578000.0,
      "maint_capex": 3204600.0,
      "owner_earnings": -16686600.0,
      "gross_margin_pct": 20.31124150661382,
      "rev_growth_pct": 5.5275023547968205
    },
    {
      "fiscal_year": "2026",
      "revenue": 789806000.0,
      "gross_profit": 159901000.0,
      "operating_income": 56911000.0,
      "net_income": 12394000.0,
      "dna": 9788000.0,
      "operating_cf": 19158000.0,
      "capex": -3696000.0,
      "free_cash_flow": 15462000.0,
      "dividends_paid": 0.0,
      "buybacks": -11351000.0,
      "total_assets": 1019437000.0,
      "total_liabilities": 753427000.0,
      "total_equity": 266010000.0,
      "cash": 14650000.0,
      "total_debt": 199587000.0,
      "current_assets": 583982000.0,
      "current_liabilities": 399596000.0,
      "shares_outstanding": 18924818.0,
      "net_wc": 184386000.0,
      "wc_change": -23940000.0,
      "capex_abs": 3696000.0,
      "maint_capex": 2587200.0,
      "owner_earnings": -4345200.0,
      "gross_margin_pct": 20.245604616829958,
      "rev_growth_pct": 4.284918281279304
    }
  ],
  "latest_oe": -4345200.0,
  "latest_cash": 14650000.0,
  "latest_debt": 199587000.0,
  "ev": 465970568.0,
  "oe_yield": -0.9325052478421769,
  "roe": 4.659223337468516,
  "debt_equity": 0.7502988609450773,
  "latest_gm": 20.245604616829958,
  "current_ratio": 1.4614310453558095,
  "latest_net_income": 12394000.0,
  "latest_dna": 9788000.0,
  "latest_wc_change": -23940000.0,
  "latest_maint_capex": 2587200.0,
  "latest_net_wc": 184386000.0,
  "latest_current_assets": 583982000.0,
  "latest_current_liabilities": 399596000.0,
  "mos_flag": "NO — yield does not compensate for business risk",
  "lolla_signals": [],
  "s1a": "YES — business model is understandable (Consumer Cyclical)",
  "search_queries": {
    "section_1": [
      "Motorcar Parts of America, Inc. MPAA revenue predictability recurring demand analysis 2025 2026",
      "Motorcar Parts of America, Inc. MPAA business model complexity investor circle of competence",
      "Motorcar Parts of America, Inc. MPAA 10 year earnings outlook business stability forecast"
    ],
    "section_2": [
      "Motorcar Parts of America, Inc. MPAA competitive moat analysis switching costs brand advantage",
      "Motorcar Parts of America, Inc. MPAA network effects scale advantages cost leadership",
      "Motorcar Parts of America, Inc. MPAA patents regulatory barriers intellectual property moat",
      "Motorcar Parts of America, Inc. MPAA competitive threats risks disruption challenges 2025 2026",
      "Motorcar Parts of America, Inc. MPAA moat widening narrowing competitive position trend"
    ],
    "section_3": [
      "Motorcar Parts of America, Inc. MPAA CEO management candor shareholder letter transparency",
      "Motorcar Parts of America, Inc. MPAA executive compensation insider ownership stock options proxy",
      "Motorcar Parts of America, Inc. MPAA key man risk CEO succession plan leadership"
    ],
    "section_5": [
      "Motorcar Parts of America, Inc. MPAA stock valuation fair value analyst price target 2025 2026"
    ],
    "section_6": [
      "Motorcar Parts of America, Inc. MPAA investor sentiment hype contrarian analysis bias"
    ],
    "section_7": [
      "Motorcar Parts of America, Inc. MPAA market position monopoly commodity pricing power ecosystem",
      "Motorcar Parts of America, Inc. MPAA growth engines expansion opportunities critical mass"
    ],
    "section_8": [
      "Motorcar Parts of America, Inc. MPAA investment thesis bull bear case converging forces"
    ],
    "section_9": [
      "Motorcar Parts of America, Inc. MPAA investment risk permanent capital loss downside analysis",
      "Motorcar Parts of America, Inc. MPAA opportunity cost alternative investments comparison"
    ]
  },
  "risk_free_rate": 4.35,
  "maint_capex_ratio": 0.7,
  "fetch_date": "2026-06-16"
}