{
  "ticker": "OBDC",
  "company_name": "Blue Owl Capital Corporation",
  "sector": "Financial Services",
  "industry": "Asset Management",
  "description": "Blue Owl Capital Corporation is a business development company. It specializes in direct and fund of fund investments. The fund makes investments in senior secured, direct lending or unsecured loans, subordinated loans or mezzanine loans and also considers equity-related securities including warrants and preferred stocks also pursues preferred equity investments, first lien, unitranche, and second lien term loans and common equity investments. Within private equity, it seeks to invest in growth, acquisitions, market or product expansion, refinancings and recapitalizations. It seeks to invest i",
  "employees": "N/A",
  "exchange": "NYQ",
  "website": "https://www.blueowlcapitalcorporation.com",
  "current_price": 11.08,
  "market_cap": 5499063808.0,
  "shares_out": 496305424.0,
  "pe_ratio": 15.828571,
  "financial_data": [
    {
      "fiscal_year": "2021",
      "revenue": null,
      "gross_profit": null,
      "operating_income": null,
      "net_income": null,
      "dna": null,
      "operating_cf": 0.0,
      "capex": 0.0,
      "free_cash_flow": 0.0,
      "dividends_paid": 0.0,
      "buybacks": 0.0,
      "total_assets": 0.0,
      "total_liabilities": 0.0,
      "total_equity": 0.0,
      "cash": 0.0,
      "total_debt": 0.0,
      "current_assets": 0.0,
      "current_liabilities": 0.0,
      "shares_outstanding": 0.0,
      "net_wc": 0.0,
      "wc_change": -0.0,
      "capex_abs": 0.0,
      "maint_capex": 0.0,
      "owner_earnings": null,
      "gross_margin_pct": null,
      "rev_growth_pct": null
    },
    {
      "fiscal_year": "2022",
      "revenue": 535625000.0,
      "gross_profit": 0.0,
      "operating_income": 0.0,
      "net_income": 466355000.0,
      "dna": 0.0,
      "operating_cf": 217268000.0,
      "capex": 0.0,
      "free_cash_flow": 217268000.0,
      "dividends_paid": -488422000.0,
      "buybacks": -25958000.0,
      "total_assets": 13584853000.0,
      "total_liabilities": 7702450000.0,
      "total_equity": 5882403000.0,
      "cash": 348667000.0,
      "total_debt": 7281744000.0,
      "current_assets": 0.0,
      "current_liabilities": 0.0,
      "shares_outstanding": 392476687.0,
      "net_wc": 0.0,
      "wc_change": -0.0,
      "capex_abs": 0.0,
      "maint_capex": 0.0,
      "owner_earnings": 466355000.0,
      "gross_margin_pct": 0.0,
      "rev_growth_pct": null
    },
    {
      "fiscal_year": "2023",
      "revenue": 838615000.0,
      "gross_profit": 0.0,
      "operating_income": 0.0,
      "net_income": 793312000.0,
      "dna": 0.0,
      "operating_cf": 1135611000.0,
      "capex": 0.0,
      "free_cash_flow": 1135611000.0,
      "dividends_paid": -613374000.0,
      "buybacks": -34058000.0,
      "total_assets": 13511396000.0,
      "total_liabilities": 7490003000.0,
      "total_equity": 6021393000.0,
      "cash": 572591000.0,
      "total_debt": 7077088000.0,
      "current_assets": 0.0,
      "current_liabilities": 0.0,
      "shares_outstanding": 389732868.0,
      "net_wc": 0.0,
      "wc_change": -0.0,
      "capex_abs": 0.0,
      "maint_capex": 0.0,
      "owner_earnings": 793312000.0,
      "gross_margin_pct": 0.0,
      "rev_growth_pct": 56.56756126021003
    },
    {
      "fiscal_year": "2024",
      "revenue": 665750000.0,
      "gross_profit": 0.0,
      "operating_income": 0.0,
      "net_income": 594980000.0,
      "dna": 0.0,
      "operating_cf": 160215000.0,
      "capex": 0.0,
      "free_cash_flow": 160215000.0,
      "dividends_paid": -655558000.0,
      "buybacks": 0.0,
      "total_assets": 13865564000.0,
      "total_liabilities": 7912723000.0,
      "total_equity": 5952841000.0,
      "cash": 431769000.0,
      "total_debt": 7457702000.0,
      "current_assets": 0.0,
      "current_liabilities": 0.0,
      "shares_outstanding": 390217304.0,
      "net_wc": 0.0,
      "wc_change": -0.0,
      "capex_abs": 0.0,
      "maint_capex": 0.0,
      "owner_earnings": 594980000.0,
      "gross_margin_pct": 0.0,
      "rev_growth_pct": -20.613153831019005
    },
    {
      "fiscal_year": "2025",
      "revenue": 709659000.0,
      "gross_profit": 0.0,
      "operating_income": 0.0,
      "net_income": 627407000.0,
      "dna": 0.0,
      "operating_cf": 1741520000.0,
      "capex": 0.0,
      "free_cash_flow": 1741520000.0,
      "dividends_paid": -752524000.0,
      "buybacks": -148200000.0,
      "total_assets": 17186365000.0,
      "total_liabilities": 9789086000.0,
      "total_equity": 7397279000.0,
      "cash": 521094000.0,
      "total_debt": 9300076000.0,
      "current_assets": 0.0,
      "current_liabilities": 0.0,
      "shares_outstanding": 499448499.0,
      "net_wc": 0.0,
      "wc_change": -0.0,
      "capex_abs": 0.0,
      "maint_capex": 0.0,
      "owner_earnings": 627407000.0,
      "gross_margin_pct": 0.0,
      "rev_growth_pct": 6.5954187007134735
    }
  ],
  "latest_oe": 627407000.0,
  "latest_cash": 521094000.0,
  "latest_debt": 9300076000.0,
  "ev": 14278045808.0,
  "oe_yield": 4.3942077819113265,
  "roe": 8.481591677155883,
  "debt_equity": 1.2572293136435708,
  "latest_gm": 0.0,
  "current_ratio": 0.0,
  "latest_net_income": 627407000.0,
  "latest_dna": 0.0,
  "latest_wc_change": -0.0,
  "latest_maint_capex": 0.0,
  "latest_net_wc": 0.0,
  "latest_current_assets": 0.0,
  "latest_current_liabilities": 0.0,
  "mos_flag": "BORDERLINE — yield is close to risk-free rate",
  "lolla_signals": [
    "OE growing avg 16.9% p.a."
  ],
  "s1a": "YES — business model is understandable (Financial Services)",
  "search_queries": {
    "section_1": [
      "Blue Owl Capital Corporation OBDC revenue predictability recurring demand analysis 2025 2026",
      "Blue Owl Capital Corporation OBDC business model complexity investor circle of competence",
      "Blue Owl Capital Corporation OBDC 10 year earnings outlook business stability forecast"
    ],
    "section_2": [
      "Blue Owl Capital Corporation OBDC competitive moat analysis switching costs brand advantage",
      "Blue Owl Capital Corporation OBDC network effects scale advantages cost leadership",
      "Blue Owl Capital Corporation OBDC patents regulatory barriers intellectual property moat",
      "Blue Owl Capital Corporation OBDC competitive threats risks disruption challenges 2025 2026",
      "Blue Owl Capital Corporation OBDC moat widening narrowing competitive position trend"
    ],
    "section_3": [
      "Blue Owl Capital Corporation OBDC CEO management candor shareholder letter transparency",
      "Blue Owl Capital Corporation OBDC executive compensation insider ownership stock options proxy",
      "Blue Owl Capital Corporation OBDC key man risk CEO succession plan leadership"
    ],
    "section_5": [
      "Blue Owl Capital Corporation OBDC stock valuation fair value analyst price target 2025 2026"
    ],
    "section_6": [
      "Blue Owl Capital Corporation OBDC investor sentiment hype contrarian analysis bias"
    ],
    "section_7": [
      "Blue Owl Capital Corporation OBDC market position monopoly commodity pricing power ecosystem",
      "Blue Owl Capital Corporation OBDC growth engines expansion opportunities critical mass"
    ],
    "section_8": [
      "Blue Owl Capital Corporation OBDC investment thesis bull bear case converging forces"
    ],
    "section_9": [
      "Blue Owl Capital Corporation OBDC investment risk permanent capital loss downside analysis",
      "Blue Owl Capital Corporation OBDC opportunity cost alternative investments comparison"
    ]
  },
  "risk_free_rate": 4.35,
  "maint_capex_ratio": 0.7,
  "fetch_date": "2026-06-16"
}