{
  "ticker": "REAX",
  "company_name": "The Real Brokerage Inc.",
  "sector": "Real Estate",
  "industry": "Real Estate Services",
  "description": "The Real Brokerage Inc., together with its subsidiaries, operates as a real estate technology company in the United States and Canada. The company provides title, mortgage, and wallet services. It also offers ancillary services including mortgage origination, title and escrow services, and financial technology and lending products. The company was founded in 2014 and is headquartered in Miami, Florida.",
  "employees": "489",
  "exchange": "NCM",
  "website": "https://www.onereal.com",
  "current_price": 1.66,
  "market_cap": 356253792.0,
  "shares_out": 214610724.0,
  "pe_ratio": 0.0,
  "financial_data": [
    {
      "fiscal_year": "2021",
      "revenue": 0.0,
      "gross_profit": 0.0,
      "operating_income": 0.0,
      "net_income": 0.0,
      "dna": 0.0,
      "operating_cf": 0.0,
      "capex": 0.0,
      "free_cash_flow": 0.0,
      "dividends_paid": 0.0,
      "buybacks": 0.0,
      "total_assets": 0.0,
      "total_liabilities": 0.0,
      "total_equity": 0.0,
      "cash": 0.0,
      "total_debt": 131000.0,
      "current_assets": 0.0,
      "current_liabilities": 0.0,
      "shares_outstanding": 0.0,
      "net_wc": 0.0,
      "wc_change": -0.0,
      "capex_abs": 0.0,
      "maint_capex": 0.0,
      "owner_earnings": 0.0,
      "gross_margin_pct": null,
      "rev_growth_pct": null
    },
    {
      "fiscal_year": "2022",
      "revenue": 381756000.0,
      "gross_profit": 31950000.0,
      "operating_income": -19746000.0,
      "net_income": -20577000.0,
      "dna": 333000.0,
      "operating_cf": 5995000.0,
      "capex": -1408000.0,
      "free_cash_flow": 4587000.0,
      "dividends_paid": 0.0,
      "buybacks": -8060000.0,
      "total_assets": 43762000.0,
      "total_liabilities": 21347000.0,
      "total_equity": 22152000.0,
      "cash": 10846000.0,
      "total_debt": 96000.0,
      "current_assets": 28369000.0,
      "current_liabilities": 21105000.0,
      "shares_outstanding": 179921874.0,
      "net_wc": 7264000.0,
      "wc_change": -7264000.0,
      "capex_abs": 1408000.0,
      "maint_capex": 985599.9999999999,
      "owner_earnings": -28493600.0,
      "gross_margin_pct": 8.36922013013548,
      "rev_growth_pct": null
    },
    {
      "fiscal_year": "2023",
      "revenue": 689158000.0,
      "gross_profit": 62873000.0,
      "operating_income": -26010000.0,
      "net_income": -27501000.0,
      "dna": 1128000.0,
      "operating_cf": 18977000.0,
      "capex": -629000.0,
      "free_cash_flow": 18348000.0,
      "dividends_paid": 0.0,
      "buybacks": -2865000.0,
      "total_assets": 64548000.0,
      "total_liabilities": 27464000.0,
      "total_equity": 36875000.0,
      "cash": 14707000.0,
      "total_debt": 0.0,
      "current_assets": 50513000.0,
      "current_liabilities": 27195000.0,
      "shares_outstanding": 183605781.0,
      "net_wc": 23318000.0,
      "wc_change": -16054000.0,
      "capex_abs": 629000.0,
      "maint_capex": 440300.0,
      "owner_earnings": -42867300.0,
      "gross_margin_pct": 9.12316188740463,
      "rev_growth_pct": 80.52316139104559
    },
    {
      "fiscal_year": "2024",
      "revenue": 1264639000.0,
      "gross_profit": 114741000.0,
      "operating_income": -15976000.0,
      "net_income": -26541000.0,
      "dna": 1396000.0,
      "operating_cf": 48731000.0,
      "capex": -1045000.0,
      "free_cash_flow": 47686000.0,
      "dividends_paid": 0.0,
      "buybacks": -36283000.0,
      "total_assets": 86595000.0,
      "total_liabilities": 54452000.0,
      "total_equity": 32146000.0,
      "cash": 23376000.0,
      "total_debt": 0.0,
      "current_assets": 72911000.0,
      "current_liabilities": 54452000.0,
      "shares_outstanding": 202499045.0,
      "net_wc": 18459000.0,
      "wc_change": 4859000.0,
      "capex_abs": 1045000.0,
      "maint_capex": 731500.0,
      "owner_earnings": -21017500.0,
      "gross_margin_pct": 9.07302400131579,
      "rev_growth_pct": 83.50494371392337
    },
    {
      "fiscal_year": "2025",
      "revenue": 1968416000.0,
      "gross_profit": 165688000.0,
      "operating_income": -8497000.0,
      "net_income": -8105000.0,
      "dna": 1929000.0,
      "operating_cf": 65926000.0,
      "capex": -3850000.0,
      "free_cash_flow": 62076000.0,
      "dividends_paid": 0.0,
      "buybacks": -39363000.0,
      "total_assets": 126861000.0,
      "total_liabilities": 75276000.0,
      "total_equity": 51675000.0,
      "cash": 33213000.0,
      "total_debt": 0.0,
      "current_assets": 105764000.0,
      "current_liabilities": 75266000.0,
      "shares_outstanding": 210478000.0,
      "net_wc": 30498000.0,
      "wc_change": -12039000.0,
      "capex_abs": 3850000.0,
      "maint_capex": 2695000.0,
      "owner_earnings": -20910000.0,
      "gross_margin_pct": 8.41732641880578,
      "rev_growth_pct": 55.65042672256668
    }
  ],
  "latest_oe": -20910000.0,
  "latest_cash": 33213000.0,
  "latest_debt": 0.0,
  "ev": 323040792.0,
  "oe_yield": -6.472866745571872,
  "roe": -15.684567005321723,
  "debt_equity": 0.0,
  "latest_gm": 8.41732641880578,
  "current_ratio": 1.4052028804506682,
  "latest_net_income": -8105000.0,
  "latest_dna": 1929000.0,
  "latest_wc_change": -12039000.0,
  "latest_maint_capex": 2695000.0,
  "latest_net_wc": 30498000.0,
  "latest_current_assets": 105764000.0,
  "latest_current_liabilities": 75266000.0,
  "mos_flag": "NO — yield does not compensate for business risk",
  "lolla_signals": [
    "Low leverage (0.00x D/E)"
  ],
  "s1a": "YES — business model is understandable (Real Estate)",
  "search_queries": {
    "section_1": [
      "The Real Brokerage Inc. REAX revenue predictability recurring demand analysis 2025 2026",
      "The Real Brokerage Inc. REAX business model complexity investor circle of competence",
      "The Real Brokerage Inc. REAX 10 year earnings outlook business stability forecast"
    ],
    "section_2": [
      "The Real Brokerage Inc. REAX competitive moat analysis switching costs brand advantage",
      "The Real Brokerage Inc. REAX network effects scale advantages cost leadership",
      "The Real Brokerage Inc. REAX patents regulatory barriers intellectual property moat",
      "The Real Brokerage Inc. REAX competitive threats risks disruption challenges 2025 2026",
      "The Real Brokerage Inc. REAX moat widening narrowing competitive position trend"
    ],
    "section_3": [
      "The Real Brokerage Inc. REAX CEO management candor shareholder letter transparency",
      "The Real Brokerage Inc. REAX executive compensation insider ownership stock options proxy",
      "The Real Brokerage Inc. REAX key man risk CEO succession plan leadership"
    ],
    "section_5": [
      "The Real Brokerage Inc. REAX stock valuation fair value analyst price target 2025 2026"
    ],
    "section_6": [
      "The Real Brokerage Inc. REAX investor sentiment hype contrarian analysis bias"
    ],
    "section_7": [
      "The Real Brokerage Inc. REAX market position monopoly commodity pricing power ecosystem",
      "The Real Brokerage Inc. REAX growth engines expansion opportunities critical mass"
    ],
    "section_8": [
      "The Real Brokerage Inc. REAX investment thesis bull bear case converging forces"
    ],
    "section_9": [
      "The Real Brokerage Inc. REAX investment risk permanent capital loss downside analysis",
      "The Real Brokerage Inc. REAX opportunity cost alternative investments comparison"
    ]
  },
  "risk_free_rate": 4.35,
  "maint_capex_ratio": 0.7,
  "fetch_date": "2026-06-16"
}