{
  "ticker": "RGC",
  "company_name": "Regencell Bioscience Holdings Limited",
  "sector": "Healthcare",
  "industry": "Drug Manufacturers - Specialty & Generic",
  "description": "Regencell Bioscience Holdings Limited operates as a Traditional Chinese medicine (TCM) bioscience company in Hong Kong. It focuses on the research, development, and commercialization of TCM for the treatment of neurocognitive disorders and degeneration, primarily for attention deficit hyperactivity disorder and autism spectrum disorder. The company was incorporated in 2014 and is headquartered in Causeway Bay, Hong Kong.",
  "employees": "10",
  "exchange": "NCM",
  "website": "https://www.regencellbioscience.com",
  "current_price": 17.09,
  "market_cap": 8450815488.0,
  "shares_out": 494488908.0,
  "pe_ratio": 0.0,
  "financial_data": [
    {
      "fiscal_year": "2021",
      "revenue": 0.0,
      "gross_profit": 0.0,
      "operating_income": -1381362.0,
      "net_income": -1346745.0,
      "dna": 26456.0,
      "operating_cf": -767311.0,
      "capex": 0.0,
      "free_cash_flow": -767311.0,
      "dividends_paid": 0.0,
      "buybacks": 0.0,
      "total_assets": 340134.0,
      "total_liabilities": 4337771.0,
      "total_equity": -3997637.0,
      "cash": 59413.0,
      "total_debt": 3681969.0,
      "current_assets": 66849.0,
      "current_liabilities": 4337771.0,
      "shares_outstanding": 480399990.0,
      "net_wc": -4270922.0,
      "wc_change": -0.0,
      "capex_abs": 0.0,
      "maint_capex": 0.0,
      "owner_earnings": -1320289.0,
      "gross_margin_pct": null,
      "rev_growth_pct": null
    },
    {
      "fiscal_year": "2022",
      "revenue": 0.0,
      "gross_profit": 0.0,
      "operating_income": -7617770.0,
      "net_income": -7445943.0,
      "dna": 604397.0,
      "operating_cf": -5267055.0,
      "capex": -780876.0,
      "free_cash_flow": -6047931.0,
      "dividends_paid": 0.0,
      "buybacks": 0.0,
      "total_assets": 18018918.0,
      "total_liabilities": 938032.0,
      "total_equity": 17065498.0,
      "cash": 6416998.0,
      "total_debt": 771255.0,
      "current_assets": 16444596.0,
      "current_liabilities": 577764.0,
      "shares_outstanding": 494488908.0,
      "net_wc": 15866832.0,
      "wc_change": -20137754.0,
      "capex_abs": 780876.0,
      "maint_capex": 546613.2,
      "owner_earnings": -27525913.2,
      "gross_margin_pct": null,
      "rev_growth_pct": null
    },
    {
      "fiscal_year": "2023",
      "revenue": 0.0,
      "gross_profit": 0.0,
      "operating_income": -6273671.0,
      "net_income": -5871130.0,
      "dna": 769687.0,
      "operating_cf": -4962949.0,
      "capex": -27392.0,
      "free_cash_flow": -4990341.0,
      "dividends_paid": 0.0,
      "buybacks": 0.0,
      "total_assets": 12621755.0,
      "total_liabilities": 632320.0,
      "total_equity": 12030333.0,
      "cash": 1564795.0,
      "total_debt": 463669.0,
      "current_assets": 11621343.0,
      "current_liabilities": 606914.0,
      "shares_outstanding": 494488908.0,
      "net_wc": 11014429.0,
      "wc_change": 4852403.0,
      "capex_abs": 27392.0,
      "maint_capex": 19174.399999999998,
      "owner_earnings": -268214.4,
      "gross_margin_pct": null,
      "rev_growth_pct": null
    },
    {
      "fiscal_year": "2024",
      "revenue": 0.0,
      "gross_profit": 0.0,
      "operating_income": -4736726.0,
      "net_income": -4301837.0,
      "dna": 745588.0,
      "operating_cf": -4001687.0,
      "capex": -5376.0,
      "free_cash_flow": -4007063.0,
      "dividends_paid": 0.0,
      "buybacks": 0.0,
      "total_assets": 8438211.0,
      "total_liabilities": 219512.0,
      "total_equity": 8218699.0,
      "cash": 2961235.0,
      "total_debt": 85741.0,
      "current_assets": 8114013.0,
      "current_liabilities": 193578.0,
      "shares_outstanding": 494488908.0,
      "net_wc": 7920435.0,
      "wc_change": 3093994.0,
      "capex_abs": 5376.0,
      "maint_capex": 3763.2,
      "owner_earnings": -466018.2,
      "gross_margin_pct": null,
      "rev_growth_pct": null
    },
    {
      "fiscal_year": "2025",
      "revenue": 0.0,
      "gross_profit": 0.0,
      "operating_income": 0.0,
      "net_income": 0.0,
      "dna": 0.0,
      "operating_cf": null,
      "capex": null,
      "free_cash_flow": null,
      "dividends_paid": null,
      "buybacks": null,
      "total_assets": null,
      "total_liabilities": null,
      "total_equity": null,
      "cash": null,
      "total_debt": null,
      "current_assets": null,
      "current_liabilities": null,
      "shares_outstanding": null,
      "net_wc": null,
      "wc_change": -0.0,
      "capex_abs": null,
      "maint_capex": null,
      "owner_earnings": null,
      "gross_margin_pct": null,
      "rev_growth_pct": null
    }
  ],
  "latest_oe": null,
  "latest_cash": null,
  "latest_debt": null,
  "ev": null,
  "oe_yield": 0,
  "roe": null,
  "debt_equity": null,
  "latest_gm": null,
  "current_ratio": null,
  "latest_net_income": 0.0,
  "latest_dna": 0.0,
  "latest_wc_change": -0.0,
  "latest_maint_capex": null,
  "latest_net_wc": null,
  "latest_current_assets": null,
  "latest_current_liabilities": null,
  "mos_flag": "NO — yield does not compensate for business risk",
  "lolla_signals": [
    "OE growing avg 489.9% p.a."
  ],
  "s1a": "REVIEW (analyst confirmed) — complex sector: Healthcare",
  "search_queries": {
    "section_1": [
      "Regencell Bioscience Holdings Limited RGC revenue predictability recurring demand analysis 2025 2026",
      "Regencell Bioscience Holdings Limited RGC business model complexity investor circle of competence",
      "Regencell Bioscience Holdings Limited RGC 10 year earnings outlook business stability forecast"
    ],
    "section_2": [
      "Regencell Bioscience Holdings Limited RGC competitive moat analysis switching costs brand advantage",
      "Regencell Bioscience Holdings Limited RGC network effects scale advantages cost leadership",
      "Regencell Bioscience Holdings Limited RGC patents regulatory barriers intellectual property moat",
      "Regencell Bioscience Holdings Limited RGC competitive threats risks disruption challenges 2025 2026",
      "Regencell Bioscience Holdings Limited RGC moat widening narrowing competitive position trend"
    ],
    "section_3": [
      "Regencell Bioscience Holdings Limited RGC CEO management candor shareholder letter transparency",
      "Regencell Bioscience Holdings Limited RGC executive compensation insider ownership stock options proxy",
      "Regencell Bioscience Holdings Limited RGC key man risk CEO succession plan leadership"
    ],
    "section_5": [
      "Regencell Bioscience Holdings Limited RGC stock valuation fair value analyst price target 2025 2026"
    ],
    "section_6": [
      "Regencell Bioscience Holdings Limited RGC investor sentiment hype contrarian analysis bias"
    ],
    "section_7": [
      "Regencell Bioscience Holdings Limited RGC market position monopoly commodity pricing power ecosystem",
      "Regencell Bioscience Holdings Limited RGC growth engines expansion opportunities critical mass"
    ],
    "section_8": [
      "Regencell Bioscience Holdings Limited RGC investment thesis bull bear case converging forces"
    ],
    "section_9": [
      "Regencell Bioscience Holdings Limited RGC investment risk permanent capital loss downside analysis",
      "Regencell Bioscience Holdings Limited RGC opportunity cost alternative investments comparison"
    ]
  },
  "risk_free_rate": 4.35,
  "maint_capex_ratio": 0.7,
  "fetch_date": "2026-06-16"
}