{
  "ticker": "RXO",
  "company_name": "RXO, Inc.",
  "sector": "Industrials",
  "industry": "Trucking",
  "description": "RXO, Inc. engages in truck brokerage business in the United States, Canada, Mexico, Asia, and Europe. It offers truckload freight brokering services. The company also provides asset-light managed transportation and last mile services, as well as freight forwarding services, including facilitation of ocean and air transportation, customs brokerage, and additional domestic services including middle mile. RXO, Inc. was incorporated in 2022 and is headquartered in Charlotte, North Carolina.",
  "employees": "6906",
  "exchange": "NYQ",
  "website": "https://www.rxo.com",
  "current_price": 27.71,
  "market_cap": 4569942016.0,
  "shares_out": 164920312.0,
  "pe_ratio": 0.0,
  "financial_data": [
    {
      "fiscal_year": "2021",
      "revenue": 0.0,
      "gross_profit": 0.0,
      "operating_income": 0.0,
      "net_income": 0.0,
      "dna": 81000000.0,
      "operating_cf": null,
      "capex": null,
      "free_cash_flow": null,
      "dividends_paid": null,
      "buybacks": null,
      "total_assets": 0.0,
      "total_liabilities": 0.0,
      "total_equity": 0.0,
      "cash": 0.0,
      "total_debt": 0.0,
      "current_assets": 0.0,
      "current_liabilities": 0.0,
      "shares_outstanding": 0.0,
      "net_wc": 0.0,
      "wc_change": -0.0,
      "capex_abs": null,
      "maint_capex": null,
      "owner_earnings": null,
      "gross_margin_pct": null,
      "rev_growth_pct": null
    },
    {
      "fiscal_year": "2022",
      "revenue": 4796000000.0,
      "gross_profit": 860000000.0,
      "operating_income": 220000000.0,
      "net_income": 92000000.0,
      "dna": 86000000.0,
      "operating_cf": 310000000.0,
      "capex": -57000000.0,
      "free_cash_flow": 253000000.0,
      "dividends_paid": 0.0,
      "buybacks": 0.0,
      "total_assets": 2031000000.0,
      "total_liabilities": 1444000000.0,
      "total_equity": 587000000.0,
      "cash": 98000000.0,
      "total_debt": 617000000.0,
      "current_assets": 1029000000.0,
      "current_liabilities": 823000000.0,
      "shares_outstanding": 116400000.0,
      "net_wc": 206000000.0,
      "wc_change": -206000000.0,
      "capex_abs": 57000000.0,
      "maint_capex": 39900000.0,
      "owner_earnings": -67900000.0,
      "gross_margin_pct": 17.93160967472894,
      "rev_growth_pct": null
    },
    {
      "fiscal_year": "2023",
      "revenue": 3927000000.0,
      "gross_profit": 658000000.0,
      "operating_income": 67000000.0,
      "net_income": 4000000.0,
      "dna": 67000000.0,
      "operating_cf": 89000000.0,
      "capex": -64000000.0,
      "free_cash_flow": 25000000.0,
      "dividends_paid": 0.0,
      "buybacks": -2000000.0,
      "total_assets": 1825000000.0,
      "total_liabilities": 1231000000.0,
      "total_equity": 594000000.0,
      "cash": 5000000.0,
      "total_debt": 558000000.0,
      "current_assets": 796000000.0,
      "current_liabilities": 682000000.0,
      "shares_outstanding": 117026000.0,
      "net_wc": 114000000.0,
      "wc_change": 92000000.0,
      "capex_abs": 64000000.0,
      "maint_capex": 44800000.0,
      "owner_earnings": 118200000.0,
      "gross_margin_pct": 16.755793226381464,
      "rev_growth_pct": -18.11926605504587
    },
    {
      "fiscal_year": "2024",
      "revenue": 4550000000.0,
      "gross_profit": 696000000.0,
      "operating_income": 30000000.0,
      "net_income": -290000000.0,
      "dna": 87000000.0,
      "operating_cf": -12000000.0,
      "capex": -45000000.0,
      "free_cash_flow": -57000000.0,
      "dividends_paid": 0.0,
      "buybacks": 0.0,
      "total_assets": 3414000000.0,
      "total_liabilities": 1802000000.0,
      "total_equity": 1612000000.0,
      "cash": 35000000.0,
      "total_debt": 664000000.0,
      "current_assets": 1339000000.0,
      "current_liabilities": 1065000000.0,
      "shares_outstanding": 162517000.0,
      "net_wc": 274000000.0,
      "wc_change": -160000000.0,
      "capex_abs": 45000000.0,
      "maint_capex": 31499999.999999996,
      "owner_earnings": -394500000.0,
      "gross_margin_pct": 15.296703296703296,
      "rev_growth_pct": 15.864527629233516
    },
    {
      "fiscal_year": "2025",
      "revenue": 5742000000.0,
      "gross_profit": 825000000.0,
      "operating_income": -7000000.0,
      "net_income": -100000000.0,
      "dna": 116000000.0,
      "operating_cf": 51000000.0,
      "capex": -59000000.0,
      "free_cash_flow": -8000000.0,
      "dividends_paid": 0.0,
      "buybacks": 0.0,
      "total_assets": 3277000000.0,
      "total_liabilities": 1736000000.0,
      "total_equity": 1541000000.0,
      "cash": 17000000.0,
      "total_debt": 670000000.0,
      "current_assets": 1317000000.0,
      "current_liabilities": 1038000000.0,
      "shares_outstanding": 164160000.0,
      "net_wc": 279000000.0,
      "wc_change": -5000000.0,
      "capex_abs": 59000000.0,
      "maint_capex": 41300000.0,
      "owner_earnings": -30300000.0,
      "gross_margin_pct": 14.367816091954023,
      "rev_growth_pct": 26.19780219780219
    }
  ],
  "latest_oe": -30300000.0,
  "latest_cash": 17000000.0,
  "latest_debt": 670000000.0,
  "ev": 5222942016.0,
  "oe_yield": -0.5801328045989933,
  "roe": -6.489292667099286,
  "debt_equity": 0.43478260869565216,
  "latest_gm": 14.367816091954023,
  "current_ratio": 1.26878612716763,
  "latest_net_income": -100000000.0,
  "latest_dna": 116000000.0,
  "latest_wc_change": -5000000.0,
  "latest_maint_capex": 41300000.0,
  "latest_net_wc": 279000000.0,
  "latest_current_assets": 1317000000.0,
  "latest_current_liabilities": 1038000000.0,
  "mos_flag": "NO — yield does not compensate for business risk",
  "lolla_signals": [
    "Low leverage (0.43x D/E)"
  ],
  "s1a": "YES — business model is understandable (Industrials)",
  "search_queries": {
    "section_1": [
      "RXO, Inc. RXO revenue predictability recurring demand analysis 2025 2026",
      "RXO, Inc. RXO business model complexity investor circle of competence",
      "RXO, Inc. RXO 10 year earnings outlook business stability forecast"
    ],
    "section_2": [
      "RXO, Inc. RXO competitive moat analysis switching costs brand advantage",
      "RXO, Inc. RXO network effects scale advantages cost leadership",
      "RXO, Inc. RXO patents regulatory barriers intellectual property moat",
      "RXO, Inc. RXO competitive threats risks disruption challenges 2025 2026",
      "RXO, Inc. RXO moat widening narrowing competitive position trend"
    ],
    "section_3": [
      "RXO, Inc. RXO CEO management candor shareholder letter transparency",
      "RXO, Inc. RXO executive compensation insider ownership stock options proxy",
      "RXO, Inc. RXO key man risk CEO succession plan leadership"
    ],
    "section_5": [
      "RXO, Inc. RXO stock valuation fair value analyst price target 2025 2026"
    ],
    "section_6": [
      "RXO, Inc. RXO investor sentiment hype contrarian analysis bias"
    ],
    "section_7": [
      "RXO, Inc. RXO market position monopoly commodity pricing power ecosystem",
      "RXO, Inc. RXO growth engines expansion opportunities critical mass"
    ],
    "section_8": [
      "RXO, Inc. RXO investment thesis bull bear case converging forces"
    ],
    "section_9": [
      "RXO, Inc. RXO investment risk permanent capital loss downside analysis",
      "RXO, Inc. RXO opportunity cost alternative investments comparison"
    ]
  },
  "risk_free_rate": 4.35,
  "maint_capex_ratio": 0.7,
  "fetch_date": "2026-06-16"
}