{
  "ticker": "UPBD",
  "company_name": "Upbound Group, Inc.",
  "sector": "Technology",
  "industry": "Software - Application",
  "description": "Upbound Group, Inc., a technology and data-driven company, provides financial solutions in the United States, Puerto Rico, and Mexico. It operates through four segments: Acima, Rent-A-Center, Brigit, and Mexico. The company also provides furniture, including mattresses, tires, consumer electronics, appliances, tools, handbags, computers, and accessories. In addition, it offers merchandise on an installment sales basis; and the lease-to-own transaction to consumers who do not qualify for traditional financing, the lease-to-own transaction through staffed or unstaffed kiosks located in third-par",
  "employees": "12050",
  "exchange": "NMS",
  "website": "https://www.upbound.com",
  "current_price": 18.72,
  "market_cap": 1091258496.0,
  "shares_out": 58293726.0,
  "pe_ratio": 13.183099,
  "financial_data": [
    {
      "fiscal_year": "2021",
      "revenue": 0.0,
      "gross_profit": 0.0,
      "operating_income": 0.0,
      "net_income": 0.0,
      "dna": 0.0,
      "operating_cf": null,
      "capex": null,
      "free_cash_flow": null,
      "dividends_paid": null,
      "buybacks": null,
      "total_assets": 0.0,
      "total_liabilities": 0.0,
      "total_equity": 0.0,
      "cash": 0.0,
      "total_debt": 0.0,
      "current_assets": 0.0,
      "current_liabilities": 0.0,
      "shares_outstanding": 0.0,
      "net_wc": 0.0,
      "wc_change": -0.0,
      "capex_abs": null,
      "maint_capex": null,
      "owner_earnings": null,
      "gross_margin_pct": null,
      "rev_growth_pct": null
    },
    {
      "fiscal_year": "2022",
      "revenue": 4245392000.0,
      "gross_profit": 2079532000.0,
      "operating_income": 148538000.0,
      "net_income": 12357000.0,
      "dna": 1363007000.0,
      "operating_cf": 468460000.0,
      "capex": -61387000.0,
      "free_cash_flow": 407073000.0,
      "dividends_paid": -79188000.0,
      "buybacks": -75052000.0,
      "total_assets": 2763619000.0,
      "total_liabilities": 2238473000.0,
      "total_equity": 525146000.0,
      "cash": 144141000.0,
      "total_debt": 1674414000.0,
      "current_assets": 309064000.0,
      "current_liabilities": 445168000.0,
      "shares_outstanding": 55673518.0,
      "net_wc": -136104000.0,
      "wc_change": 136104000.0,
      "capex_abs": 61387000.0,
      "maint_capex": 42970900.0,
      "owner_earnings": 1468497100.0,
      "gross_margin_pct": 48.983274100483534,
      "rev_growth_pct": null
    },
    {
      "fiscal_year": "2023",
      "revenue": 3992413000.0,
      "gross_profit": 2022258000.0,
      "operating_income": 162865000.0,
      "net_income": -5179000.0,
      "dna": 1294051000.0,
      "operating_cf": 200290000.0,
      "capex": -53402000.0,
      "free_cash_flow": 146888000.0,
      "dividends_paid": -83056000.0,
      "buybacks": -50000000.0,
      "total_assets": 2721430000.0,
      "total_liabilities": 2161058000.0,
      "total_equity": 560372000.0,
      "cash": 93705000.0,
      "total_debt": 1600062000.0,
      "current_assets": 261367000.0,
      "current_liabilities": 452247000.0,
      "shares_outstanding": 54354131.0,
      "net_wc": -190880000.0,
      "wc_change": 54776000.0,
      "capex_abs": 53402000.0,
      "maint_capex": 37381400.0,
      "owner_earnings": 1306266600.0,
      "gross_margin_pct": 50.652525177129725,
      "rev_growth_pct": -5.958907917101652
    },
    {
      "fiscal_year": "2024",
      "revenue": 4320564000.0,
      "gross_profit": 2080351000.0,
      "operating_income": 291631000.0,
      "net_income": 123478000.0,
      "dna": 1420948000.0,
      "operating_cf": 104721000.0,
      "capex": -56275000.0,
      "free_cash_flow": 48446000.0,
      "dividends_paid": -82299000.0,
      "buybacks": 0.0,
      "total_assets": 2649662000.0,
      "total_liabilities": 2020678000.0,
      "total_equity": 628984000.0,
      "cash": 60860000.0,
      "total_debt": 1582599000.0,
      "current_assets": 277025000.0,
      "current_liabilities": 371343000.0,
      "shares_outstanding": 54735950.0,
      "net_wc": -94318000.0,
      "wc_change": -96562000.0,
      "capex_abs": 56275000.0,
      "maint_capex": 39392500.0,
      "owner_earnings": 1408471500.0,
      "gross_margin_pct": 48.14998689985844,
      "rev_growth_pct": 8.219365080716855
    },
    {
      "fiscal_year": "2025",
      "revenue": 4695061000.0,
      "gross_profit": 2271709000.0,
      "operating_income": 223347000.0,
      "net_income": 73242000.0,
      "dna": 1514777000.0,
      "operating_cf": 305571000.0,
      "capex": -66863000.0,
      "free_cash_flow": 238708000.0,
      "dividends_paid": -87865000.0,
      "buybacks": 0.0,
      "total_assets": 3276081000.0,
      "total_liabilities": 2580341000.0,
      "total_equity": 695740000.0,
      "cash": 120528000.0,
      "total_debt": 1856682000.0,
      "current_assets": 481937000.0,
      "current_liabilities": 477669000.0,
      "shares_outstanding": 57935886.0,
      "net_wc": 4268000.0,
      "wc_change": -98586000.0,
      "capex_abs": 66863000.0,
      "maint_capex": 46804100.0,
      "owner_earnings": 1442628900.0,
      "gross_margin_pct": 48.385079554876924,
      "rev_growth_pct": 8.66778041015015
    }
  ],
  "latest_oe": 1442628900.0,
  "latest_cash": 120528000.0,
  "latest_debt": 1856682000.0,
  "ev": 2827412496.0,
  "oe_yield": 51.022937121517195,
  "roe": 10.527208439934459,
  "debt_equity": 2.668643458763331,
  "latest_gm": 48.385079554876924,
  "current_ratio": 1.0089350575398446,
  "latest_net_income": 73242000.0,
  "latest_dna": 1514777000.0,
  "latest_wc_change": -98586000.0,
  "latest_maint_capex": 46804100.0,
  "latest_net_wc": 4268000.0,
  "latest_current_assets": 481937000.0,
  "latest_current_liabilities": 477669000.0,
  "mos_flag": "YES — yield is attractive vs. risk-free rate",
  "lolla_signals": [
    "Pricing power (GM 48.4%)"
  ],
  "s1a": "REVIEW (analyst confirmed) — complex sector: Technology",
  "search_queries": {
    "section_1": [
      "Upbound Group, Inc. UPBD revenue predictability recurring demand analysis 2025 2026",
      "Upbound Group, Inc. UPBD business model complexity investor circle of competence",
      "Upbound Group, Inc. UPBD 10 year earnings outlook business stability forecast"
    ],
    "section_2": [
      "Upbound Group, Inc. UPBD competitive moat analysis switching costs brand advantage",
      "Upbound Group, Inc. UPBD network effects scale advantages cost leadership",
      "Upbound Group, Inc. UPBD patents regulatory barriers intellectual property moat",
      "Upbound Group, Inc. UPBD competitive threats risks disruption challenges 2025 2026",
      "Upbound Group, Inc. UPBD moat widening narrowing competitive position trend"
    ],
    "section_3": [
      "Upbound Group, Inc. UPBD CEO management candor shareholder letter transparency",
      "Upbound Group, Inc. UPBD executive compensation insider ownership stock options proxy",
      "Upbound Group, Inc. UPBD key man risk CEO succession plan leadership"
    ],
    "section_5": [
      "Upbound Group, Inc. UPBD stock valuation fair value analyst price target 2025 2026"
    ],
    "section_6": [
      "Upbound Group, Inc. UPBD investor sentiment hype contrarian analysis bias"
    ],
    "section_7": [
      "Upbound Group, Inc. UPBD market position monopoly commodity pricing power ecosystem",
      "Upbound Group, Inc. UPBD growth engines expansion opportunities critical mass"
    ],
    "section_8": [
      "Upbound Group, Inc. UPBD investment thesis bull bear case converging forces"
    ],
    "section_9": [
      "Upbound Group, Inc. UPBD investment risk permanent capital loss downside analysis",
      "Upbound Group, Inc. UPBD opportunity cost alternative investments comparison"
    ]
  },
  "risk_free_rate": 4.35,
  "maint_capex_ratio": 0.7,
  "fetch_date": "2026-06-16"
}